<idynomics>
 <simulation iterate="48" time="24.0" unit="hour">
<thickness domain="MyBiofilm" unit="um">
	<mean>35.7</mean>
	<stddev>35.96540003948243</stddev>
	<max>132.0</max>
</thickness>
<solute name="MyCOD" unit="g.L-1" resolution="8.0" nI="33" nJ="33" nK="1">
0.0;
2.5714172546147436E-9;
9.91241350422268E-10;
5.290890071803772E-10;
1.7888652181178858E-10;
9.1216136915937E-11;
4.21465945674549E-11;
4.369722363626275E-11;
3.706347276519657E-11;
5.330372378477214E-11;
1.1887285941391231E-10;
3.060394321692608E-10;
1.4230684385731188E-9;
1.5566103044839312E-9;
3.9999278865401057E-10;
3.71533271001103E-10;
2.2444210234008488E-10;
1.2438567867480063E-10;
1.117385003292068E-10;
7.24552023556163E-11;
7.20887770199804E-11;
8.117057075985011E-11;
2.3666151210648925E-10;
6.862994626166944E-10;
1.5248447741144568E-9;
3.0080850959947437E-9;
9.458701388099544E-10;
2.13832650455808E-10;
9.212298499281124E-11;
2.9264114439214676E-11;
7.111648075353576E-12;
2.3001265796401398E-12;
6.509594372840201E-13;
3.4448279447599933E-13;
0.0;
2.5714172546147436E-9;
2.5714172546147436E-9;
9.91241350422268E-10;
5.290890071803772E-10;
1.7888652181178858E-10;
9.1216136915937E-11;
4.21465945674549E-11;
4.369722363626275E-11;
3.706347276519657E-11;
5.330372378477214E-11;
1.1887285941391231E-10;
3.060394321692608E-10;
1.4230684385731188E-9;
1.5566103044839312E-9;
3.9999278865401057E-10;
3.71533271001103E-10;
2.2444210234008488E-10;
1.2438567867480063E-10;
1.117385003292068E-10;
7.24552023556163E-11;
7.20887770199804E-11;
8.117057075985011E-11;
2.3666151210648925E-10;
6.862994626166944E-10;
1.5248447741144568E-9;
3.0080850959947437E-9;
9.458701388099544E-10;
2.13832650455808E-10;
9.212298499281124E-11;
2.9264114439214676E-11;
7.111648075353576E-12;
2.3001265796401398E-12;
6.509594372840201E-13;
3.4448279447599933E-13;
3.4448279447599933E-13;
1.7555840633364394E-8;
1.7555840633364394E-8;
9.292325065773272E-9;
4.801113708605925E-9;
1.411529443260386E-9;
7.211729351672961E-10;
4.575075094847418E-10;
4.2575902905233247E-10;
3.225696961932065E-10;
4.74044927509543E-10;
9.49520926914837E-10;
2.6402140855806835E-9;
6.70303929661502E-9;
8.209585731157112E-9;
3.5372039927203066E-9;
2.6573895749058233E-9;
2.2268955978616294E-9;
1.364485086143271E-9;
1.0417162927657518E-9;
6.222013661244511E-10;
5.76491440380179E-10;
6.475704521502028E-10;
2.1609435577085827E-9;
4.387315012113208E-9;
1.0751266625715237E-8;
2.8130295108896113E-8;
8.409847205262736E-9;
1.7807598806770575E-9;
7.758486476617531E-10;
2.433264088003733E-10;
5.2953052041302446E-11;
2.027318116642255E-11;
4.097146562992283E-12;
2.5140142672920566E-12;
2.5140142672920566E-12;
9.486670995174273E-8;
9.486670995174273E-8;
7.826622642878767E-8;
3.604926503532837E-8;
1.2433860637739254E-8;
5.684273154740835E-9;
3.985006965252016E-9;
4.037150427217566E-9;
3.3261317461326433E-9;
3.320214262400538E-9;
8.08644803802923E-9;
2.1196560257587805E-8;
6.44363845430072E-8;
4.990470070750974E-8;
2.740289838468458E-8;
2.363851460724491E-8;
2.2634342962383362E-8;
1.2296256764163779E-8;
9.839786506749771E-9;
5.706589525535391E-9;
5.299168115691214E-9;
6.6191103863385365E-9;
1.348215291192782E-8;
3.979759779358458E-8;
9.754971387331306E-8;
2.0508611973716104E-7;
4.434260689469354E-8;
9.99680456200458E-9;
7.412875909819627E-9;
1.6925254048869447E-9;
5.880917059076129E-10;
1.3413561460223516E-10;
3.312444580691363E-11;
1.512028473276985E-11;
1.512028473276985E-11;
7.45764343217901E-7;
7.45764343217901E-7;
7.54904056279835E-7;
3.083784396780234E-7;
1.0321206157175737E-7;
4.602217036700796E-8;
4.001356819299048E-8;
3.5433450934423595E-8;
2.8051144185425584E-8;
2.4061809854607473E-8;
4.392794107864528E-8;
1.395118888964905E-7;
4.186513996565003E-7;
3.685193546302122E-7;
1.930722928231436E-7;
1.44006757582944E-7;
2.3639213584514595E-7;
1.2309065462796451E-7;
8.414647406974137E-8;
5.289955677579749E-8;
4.452581051820979E-8;
5.8065671626619254E-8;
1.1065518445083097E-7;
2.8637994872379333E-7;
6.625731929736814E-7;
9.138596151739704E-7;
2.7690674164205997E-7;
9.390063163279743E-8;
5.6058833010188525E-8;
1.5676769682983237E-8;
3.975722703978602E-9;
8.123695797430176E-10;
2.342358676528261E-10;
8.231428038070747E-11;
8.231428038070747E-11;
4.843374598211114E-6;
4.843374598211114E-6;
5.7833345795400245E-6;
2.708266302340334E-6;
7.530159168055797E-7;
3.5199087153798355E-7;
2.974268953707686E-7;
3.7055605950456615E-7;
2.9346464434384254E-7;
2.2389892214135095E-7;
3.7676941825197765E-7;
1.1601598122607346E-6;
3.911624664167694E-6;
3.41543276183084E-6;
1.4723556471639972E-6;
1.275317329423465E-6;
2.157827252104666E-6;
1.051491192987834E-6;
6.500513949828626E-7;
3.8882726796360486E-7;
3.616262132100119E-7;
4.3676381160640207E-7;
9.089291900814107E-7;
2.0738499484927223E-6;
5.1102887012353545E-6;
8.271025494426527E-6;
2.1820684439426166E-6;
7.249939372096629E-7;
4.4134415666724427E-7;
1.400457057926913E-7;
3.336183218654971E-8;
6.350876517608976E-9;
1.0373235252683117E-9;
3.6749882625648224E-10;
3.6749882625648224E-10;
4.0269151264392176E-5;
4.0269151264392176E-5;
3.659282239245124E-5;
2.5890400071614185E-5;
5.364381984501446E-6;
2.7314391291834353E-6;
3.179723411217282E-6;
2.3273353695592306E-6;
2.2879537168379745E-6;
2.0468328269659453E-6;
3.4417672654012496E-6;
8.902630537126865E-6;
2.6251835044060734E-5;
2.6676568490918043E-5;
1.022434622245058E-5;
1.0172834965770581E-5;
2.1903330460014022E-5;
1.143780730838038E-5;
5.8550219760460624E-6;
4.251881381330528E-6;
3.255212016788631E-6;
3.842535774374693E-6;
7.305505786598262E-6;
1.3257637239971022E-5;
3.281857167393187E-5;
4.487555686125379E-5;
1.1354542756943788E-5;
4.987472345138073E-6;
3.65542805695249E-6;
1.1541232230666725E-6;
2.320225374426888E-7;
4.181386082182352E-8;
6.4224798646889735E-9;
2.1170084512574666E-9;
2.1170084512574666E-9;
2.5976193816783824E-4;
2.5976193816783824E-4;
2.195281650659146E-4;
1.0120196862692413E-4;
3.573032857500531E-5;
2.5865191507925695E-5;
2.2194781118459317E-5;
1.9192455171754653E-5;
2.0703428557377873E-5;
1.7372393710086846E-5;
3.0863228562464324E-5;
5.217561940582967E-5;
1.0643790122535946E-4;
1.2619714703942324E-4;
6.334827709853003E-5;
6.323752116367651E-5;
9.88676789868039E-5;
7.516839225842951E-5;
5.023919401788989E-5;
3.109211309913416E-5;
2.498930441777001E-5;
3.3273133952807544E-5;
5.0667379704722174E-5;
7.003497049337574E-5;
1.6995611895756537E-4;
1.747117849085015E-4;
8.824910561415566E-5;
3.8902489769629944E-5;
3.358047999029784E-5;
9.119469668189511E-6;
1.3945618264647803E-6;
2.2702110025538144E-7;
4.291883736095531E-8;
1.0401513867711124E-8;
1.0401513867711124E-8;
4.975143804685587E-4;
4.975143804685587E-4;
4.504224317008055E-4;
3.478753343458738E-4;
1.563412630647837E-4;
1.2896603286460432E-4;
1.593350029828419E-4;
1.4973801826837174E-4;
1.886081243019842E-4;
1.6149627746452538E-4;
2.0078093586584284E-4;
3.3864806991097294E-4;
3.34298949965274E-4;
4.053979931238149E-4;
3.4781115609025423E-4;
3.0878447171275034E-4;
4.041094756267902E-4;
4.004714239783569E-4;
3.2466240547994414E-4;
2.449491742243012E-4;
1.675189162572871E-4;
2.0179969298467936E-4;
3.145930561278011E-4;
3.1182857619940606E-4;
3.7854704369029527E-4;
3.741181086448941E-4;
3.2467894581466954E-4;
2.577151387082234E-4;
1.8012884096371722E-4;
5.4449521124869765E-5;
7.318845976774249E-6;
1.0847081100360666E-6;
1.4357365403902998E-7;
5.164225763719755E-8;
5.164225763719755E-8;
7.823350990002324E-4;
7.823350990002324E-4;
7.367277714225961E-4;
6.397027250690509E-4;
4.624469022707674E-4;
4.665857884793699E-4;
5.649200304091955E-4;
6.027665196750771E-4;
6.329029421008529E-4;
6.483423749474505E-4;
6.795298520318033E-4;
7.244554309512564E-4;
7.548712288421028E-4;
7.724809980428189E-4;
7.712064912036186E-4;
7.621680497802216E-4;
7.682148274950813E-4;
7.57819797474873E-4;
7.289441342874667E-4;
6.84913920373599E-4;
6.467710318166018E-4;
6.429567247114845E-4;
6.560947976647008E-4;
6.597750083651674E-4;
6.515737584200374E-4;
6.18521561100526E-4;
5.549567584228963E-4;
4.652598826771753E-4;
3.4752849531070705E-4;
1.6970846760940283E-4;
2.838947442883727E-5;
3.6947869567795675E-6;
7.007426887421014E-7;
2.2130043246473604E-7;
2.2130043246473604E-7;
0.00111269019961525;
0.00111269019961525;
0.0010744273696657264;
9.939713242042975E-4;
8.483168133272811E-4;
9.294933766590195E-4;
9.805812221228875E-4;
0.0010181425652975046;
0.0010474442685683332;
0.0010706922613570944;
0.0010966430624744334;
0.0011246998843908722;
0.00114616673562543;
0.0011583696834470483;
0.0011599998126398947;
0.00115505070643907;
0.0011487358524988505;
0.0011335716791161133;
0.0011079272728537779;
0.0010749250484545939;
0.001043746892049729;
0.0010229798142367503;
0.0010070317948082843;
9.847410698662902E-4;
9.494290888481828E-4;
8.933740363325194E-4;
8.113475006111421E-4;
7.007903138029762E-4;
5.572222805648007E-4;
3.7260406957677074E-4;
1.1094468172590536E-4;
1.615281525510943E-5;
2.764438094984272E-6;
7.62307009087018E-7;
7.62307009087018E-7;
0.0014812574546177815;
0.0014812574546177815;
0.0014542202725992147;
0.001398840666089341;
0.0012989685370789368;
0.0013680498907341922;
0.0014096734648469218;
0.0014417458317936439;
0.0014679397849453781;
0.0014903053587936811;
0.0015115452891799497;
0.0015314981867492353;
0.001546614911170868;
0.0015547934810414923;
0.0015552585228878859;
0.0015492611753513859;
0.0015379930671851627;
0.0015197665210263324;
0.0014941585940720867;
0.0014630765032251174;
0.0014302076448207343;
0.0013981497687238496;
0.0013642106713420454;
0.0013226954044906634;
0.0012679317341281588;
0.0011941677755658295;
0.001096185676690484;
9.693072557141341E-4;
8.079067059751263E-4;
6.060714587370555E-4;
3.629692740145145E-4;
7.02192783057313E-5;
1.2589473272334631E-5;
3.1406663918920193E-6;
3.1406663918920193E-6;
0.0018767298215710663;
0.0018767298215710663;
0.0018623118085713427;
0.0018380870677467149;
0.0018205017011798553;
0.0018270280219585585;
0.0018482730649270452;
0.0018710939678306504;
0.0018922183876030486;
0.0019109056562924076;
0.0019276874552408615;
0.0019429886192109528;
0.001953952401129372;
0.0019587827210388407;
0.0019569299652339336;
0.0019485935246733813;
0.0019341592947847426;
0.0019131959239298277;
0.001885815793456117;
0.00185287244853673;
0.001815810875058809;
0.0017750639277955916;
0.001728920944448711;
0.0016737671348004584;
0.0016053925045302372;
0.0015190593437127934;
0.001409882887745422;
0.001272245610659927;
0.0010989971512607175;
8.80738758898796E-4;
6.101499621892925E-4;
2.1668921630626814E-4;
3.867543034782267E-5;
1.7630091472336964E-5;
1.7630091472336964E-5;
0.002286538114205138;
0.002286538114205138;
0.0022800456461868094;
0.0022706392504900233;
0.0022656068195703997;
0.0022712320890592766;
0.0022851292330820835;
0.002302082057831636;
0.0023187621335051143;
0.0023333532306715745;
0.0023451331237721034;
0.0023587565159053966;
0.0023672415615071216;
0.0023693939074945127;
0.0023649010910852574;
0.002353962290472988;
0.0023366713669170577;
0.0023129814037606204;
0.0022828562046200945;
0.0022467274071682804;
0.002204924650612155;
0.002157316839777019;
0.0021024736118841546;
0.0020380049105015487;
0.0019606526676055054;
0.0018667434232010978;
0.001751897328811969;
0.0016107511148942696;
0.0014349802808679615;
0.001207703881260165;
9.407850517641155E-4;
5.466277506760373E-4;
1.789755667581292E-4;
1.0631035681723215E-4;
1.0631035681723215E-4;
0.0027026408398780053;
0.0027026408398780053;
0.002700627323841961;
0.002698618239417632;
0.0026999874874074838;
0.002706962575954483;
0.0027188619215953494;
0.0027331372593456748;
0.0027473255279054296;
0.002758401664289032;
0.00276066440309184;
0.0027794477638324387;
0.002786791062559355;
0.0027864320246773636;
0.0027792451926123654;
0.002765464375657858;
0.0027455097186949652;
0.0027189852893947162;
0.002685828508109273;
0.0026460436488174905;
0.0025997734736501465;
0.0025465983454592083;
0.0024855840139761643;
0.0024149273650940785;
0.0023324053352527198;
0.002235177551221657;
0.0021201524792388046;
0.0019837138232115725;
0.0018224178723070929;
0.0016148985876071893;
0.0013592054101929634;
0.0010089790681947171;
6.604139626065329E-4;
5.270265348607682E-4;
5.270265348607682E-4;
0.0031206405743672656;
0.0031206405743672656;
0.003120970670725859;
0.0031231406825073357;
0.0031285261035321104;
0.0031376895852384813;
0.003149978922263004;
0.0031641989480325878;
0.0031787571249763287;
0.0031921815096998688;
0.00320373951293179;
0.0032114957398094936;
0.0032137913683012546;
0.003210213675310739;
0.0031999302815075075;
0.0031830559324552365;
0.003160665609237439;
0.0031315377635475774;
0.003095179431310729;
0.0030517626976977142;
0.00300128236453012;
0.0029436383762378366;
0.0028780982056854326;
0.0028036370523114407;
0.002718634290700135;
0.0026213345322522457;
0.002509605459498817;
0.0023814650691813977;
0.002235135327491172;
0.0020702139992188275;
0.001862549969182035;
0.0016555262225432202;
0.001466482811436743;
0.0013704945488273194;
0.0013704945488273194;
0.0035380398222423794;
0.0035380398222423794;
0.0035393838608476984;
0.003544175727752281;
0.0035531956331632322;
0.0035650159403006107;
0.0035790731113543345;
0.003594644291489122;
0.003611229192882068;
0.003628706700942813;
0.003650532485089866;
0.003647949097267458;
0.003646569835869384;
0.0036404152984277106;
0.0036271109412821198;
0.0036058778586265986;
0.0035824638977917855;
0.003551036522759423;
0.0035114943573683493;
0.0034642640078227146;
0.003409861736191114;
0.0033482975936887246;
0.0032794419608268574;
0.003202617544988381;
0.003117071342080094;
0.0030216591554087;
0.0029153846087537913;
0.002797157712682251;
0.0026663647546374828;
0.002522515818877066;
0.0023651828197886497;
0.0022192408827037026;
0.0020988275100179664;
0.002033452297214828;
0.002033452297214828;
0.003953940375735183;
0.003953940375735183;
0.003954039157376798;
0.003960879218962334;
0.003974752966148467;
0.003990001194970005;
0.004006339450545733;
0.004023970982171389;
0.004042493003507437;
0.004060778044089236;
0.004076742813878579;
0.004083092449650492;
0.0040838064110470485;
0.0040776609611152086;
0.004061903694279737;
0.004030775140836929;
0.004011959686884614;
0.003978544787310194;
0.003935182600296694;
0.003883832476018015;
0.0038252900744085824;
0.0037601444039669883;
0.003688444734312784;
0.003610217271241494;
0.00352506955978976;
0.0034327456893194904;
0.003332819129263939;
0.0032253192424997767;
0.0031103651724801794;
0.002988209349143573;
0.002856156866937896;
0.0027573406840664034;
0.00267588311051874;
0.002630911769978756;
0.002630911769978756;
0.0043693909393870784;
0.0043693909393870784;
0.004361836222312273;
0.004370197735483299;
0.004394818604205873;
0.0044135444966007156;
0.004432195270524578;
0.004452055952675887;
0.00447387687981403;
0.004494819864829201;
0.00451245185215474;
0.004523523837398751;
0.004527786782369256;
0.00452417310316884;
0.004511952765775613;
0.004488826814068584;
0.004455940144587943;
0.004415656208586163;
0.004366743836776098;
0.004310248549874913;
0.0042472066212188;
0.004178200314539571;
0.00410386032655935;
0.004024393033826529;
0.003940129471748315;
0.00385109310314609;
0.003757713747434757;
0.0036605982728342896;
0.0035614564224895587;
0.003463471796760888;
0.003364635454581053;
0.003277764918664856;
0.003216348240395926;
0.0031830897032931664;
0.0031830897032931664;
0.004792198658706254;
0.004792198658706254;
0.004796829175290034;
0.00480678460664327;
0.004820386057697032;
0.004837032280416054;
0.004856451442277349;
0.004878051583913979;
0.004905754555319626;
0.004932045546502106;
0.004954343027479455;
0.004970639187696139;
0.004979271826778349;
0.004979168449047269;
0.004970232643582703;
0.004956530072801185;
0.004910244583181323;
0.004861272841789597;
0.004805517395741752;
0.004743086970615668;
0.004674713176959024;
0.004601464326596235;
0.004524024945026953;
0.00444323831565206;
0.004359580788797608;
0.004273655988097613;
0.00418596165612578;
0.004097776102840907;
0.004011008728811686;
0.003929575597384329;
0.0038607844259341585;
0.0037812972387021686;
0.0037282820316001243;
0.003701823078919969;
0.003701823078919969;
0.005210403922040733;
0.005210403922040733;
0.005227472586974884;
0.0052382045078031925;
0.005241403164965949;
0.00525731492561064;
0.005278384118478071;
0.005297522918339436;
0.005338905555455144;
0.0053728553940706565;
0.005402100934640764;
0.00542502064730337;
0.005439361837722468;
0.005442607435037207;
0.005433150154135304;
0.005409665924920346;
0.005367106051725929;
0.005313284141776275;
0.005250834983026787;
0.0051814726804665315;
0.005106961138241913;
0.005028513937428082;
0.00494740015935817;
0.004864540494978755;
0.004781159846532919;
0.004697566238827143;
0.004614558834866024;
0.00453310731652672;
0.004455083163849198;
0.004382605042677073;
0.004317869704998489;
0.004257924624553935;
0.004213515390007549;
0.004193665294777503;
0.004193665294777503;
0.005611295310710334;
0.005611295310710334;
0.0056209071048851774;
0.00563385366195976;
0.005649228152963143;
0.005672282740780276;
0.005701783954891652;
0.005738718800773912;
0.005779045815992561;
0.005818224817699766;
0.005855761208603025;
0.005887842309847718;
0.005910141091514697;
0.005918615493664022;
0.005909697241564414;
0.005881744869228502;
0.005834831001853715;
0.005773788289112421;
0.0057026578505178565;
0.005624869231957403;
0.005542723004964773;
0.005458086763108328;
0.005372083976667318;
0.005286215107493204;
0.005202499126501366;
0.005120736790049759;
0.005041133342291795;
0.0049648533837336525;
0.004893133275644996;
0.00482773062218181;
0.004769678300689811;
0.004718853249539424;
0.0046737001554529355;
0.004665411929776747;
0.004665411929776747;
0.006002038884738648;
0.006002038884738648;
0.006010828895261074;
0.006026547246877197;
0.006049199728968146;
0.006080295081833888;
0.006121277794887814;
0.006176058050207259;
0.006216145429165662;
0.006264784823519637;
0.006314730769857548;
0.006360022965873878;
0.006394607170609653;
0.006411612890002293;
0.006405145222073822;
0.006372387040724132;
0.006316550667188045;
0.006243972456776999;
0.006160999867594941;
0.006072197184496244;
0.0059808288874549035;
0.0058885775213186;
0.005796480191245368;
0.005705264857472799;
0.005621723365208944;
0.0055412538967403325;
0.005464215797228759;
0.005391524919168996;
0.005324691252360655;
0.005264974978844559;
0.005214080405748101;
0.0051735686835842655;
0.005143854121732319;
0.005128323882705611;
0.005128323882705611;
0.006383702409707456;
0.006383702409707456;
0.006393247631311239;
0.006412117377453656;
0.00644017267016422;
0.006478239149640595;
0.0065264491155762735;
0.006584187134184909;
0.0066442081003968015;
0.00670988343406874;
0.0067779116863595345;
0.006842770274681745;
0.006896245115847254;
0.006927951741390656;
0.006926495046905592;
0.006885977528161845;
0.0068146181819929595;
0.006724416177088316;
0.006624756124525584;
0.006521947065757351;
0.006419372517023299;
0.006318760216850827;
0.006219517321083531;
0.006116476081608704;
0.006037366628996997;
0.005958164597064857;
0.005882412428392943;
0.0058121549133817885;
0.0057485676036353565;
0.005693205656689336;
0.005647515765239669;
0.005614318223348124;
0.005599249888623417;
0.00557695844555856;
0.00557695844555856;
0.006755203589673976;
0.006755203589673976;
0.0067661375886170225;
0.006787900897716059;
0.006820938383994477;
0.00686547142611713;
0.00692190975711269;
0.0069895117026437395;
0.007066451221098656;
0.007152163362756507;
0.007244116012330634;
0.00733649009045029;
0.007419521304876742;
0.007477081325411677;
0.007486783832159155;
0.007430044108097956;
0.007331403200067312;
0.007213929528827988;
0.007091525792219846;
0.006971037521828689;
0.00685580516228905;
0.006747107878614693;
0.006646190350295281;
0.006546232786005415;
0.006452926238986617;
0.0063710783730907584;
0.006294925455999949;
0.006225531760147905;
0.006164018565508222;
0.006111151505161253;
0.006068250072347872;
0.006036304074999638;
0.006016114542204803;
0.006002655719384723;
0.006002655719384723;
0.0071154459781424964;
0.0071154459781424964;
0.0071275580144164515;
0.007152200425116604;
0.007189598937937213;
0.007240602201611054;
0.007305647305192289;
0.007385322061436876;
0.007479427852591514;
0.0075880497531167004;
0.007709477741748317;
0.00783942353925852;
0.007967912404040909;
0.008073956790270703;
0.008113191558156143;
0.008015902470461671;
0.007866679531380635;
0.007708252038858972;
0.0075559949177056345;
0.007414734998089274;
0.007285267157750223;
0.007167521664122943;
0.007061429725972154;
0.006969186372448207;
0.006865829035547958;
0.00677810961704043;
0.006700095361167225;
0.006630825856472606;
0.006570198824236355;
0.006518917208258909;
0.006477372400812807;
0.006446310015693249;
0.006425571063700833;
0.006414551924990719;
0.006414551924990719;
0.007462908708991488;
0.007462908708991488;
0.007476227663499554;
0.007503100235725704;
0.00754444654084017;
0.007601096068092878;
0.007674567065620289;
0.00776617674132629;
0.007877726831064517;
0.00801069180642835;
0.008166190383527191;
0.008343466152254037;
0.008538645223112162;
0.008737366434415587;
0.008876036268590336;
0.00865342390914629;
0.008411061958035253;
0.008196080904277002;
0.008009348470607785;
0.00784625516256346;
0.007702867602358342;
0.007575834928621965;
0.0074626610028126865;
0.007360460126281387;
0.007262914560327876;
0.007174871186091528;
0.0070963228224864726;
0.00702686120054922;
0.006966819936504999;
0.006916286632938583;
0.006875785981150924;
0.006845301768348229;
0.006825073312086528;
0.006814721604019973;
0.006814721604019973;
0.0077967138567828715;
0.0077967138567828715;
0.007810679473803344;
0.00783930975988144;
0.007883368408982735;
0.007944570532144873;
0.008024794612677721;
0.008126920376541929;
0.008254150207270723;
0.008410663879867383;
0.008600774156912249;
0.008829506628145675;
0.009105594466819867;
0.009460762650352476;
0.01;
0.009310629769889093;
0.008927828530972449;
0.00865556921299643;
0.008438749321410918;
0.008257952189912857;
0.008103725964309501;
0.007970148174045498;
0.00785246251574686;
0.007746914540625305;
0.007649974492096915;
0.007561952006332492;
0.007482877845942291;
0.007413270725963201;
0.007353292884138664;
0.007303401508931341;
0.007263500272701508;
0.007233804010855073;
0.00721398855954637;
0.007204179463569517;
0.007204179463569517;
0.008115888059856647;
0.008115888059856647;
0.008130247498589585;
0.008159455727032689;
0.008204943023514169;
0.008268449028960428;
0.00835294225154437;
0.0084620767343037;
0.008601146537033293;
0.008776673031411936;
0.00899663515827207;
0.009267959843893028;
0.009593409008564433;
0.01;
0.01;
0.009661161152527952;
0.009333996513452462;
0.009059397666664224;
0.008832038420990854;
0.008642769861229615;
0.008483819250974549;
0.008348182100885067;
0.008229984290044139;
0.008124299841403759;
0.008027950529075449;
0.007939552440145064;
0.007859776556775167;
0.007789453961721223;
0.007729469957143435;
0.0076798752713389965;
0.007640784506382846;
0.007611735798404114;
0.007592662344022835;
0.00758311798723043;
0.00758311798723043;
0.00842038183071116;
0.00842038183071116;
0.008434339851593194;
0.00846311924129667;
0.00850792015805002;
0.008571158556600832;
0.008655950709692908;
0.008767148561435748;
0.008911301316623974;
0.009098140467933597;
0.009340891972268645;
0.009652234431855238;
0.01;
0.01;
0.01;
0.01;
0.009687486606714923;
0.00941593125722933;
0.009187022831254584;
0.008997182835655967;
0.00884029752037394;
0.008708662321122485;
0.008594612088358138;
0.008492209834442809;
0.008397518752465832;
0.008308365357705958;
0.008226692181172017;
0.008155109936062936;
0.00809466353588293;
0.008045637140294265;
0.00800738290363812;
0.00797947066412725;
0.007961131804053253;
0.007952168755858299;
0.007952168755858299;
0.0087103245854558;
0.0087103245854558;
0.008723415956897403;
0.008750199914072943;
0.00879228111831841;
0.008851817941395012;
0.00893240221661083;
0.009038868134627549;
0.009178657633566328;
0.00936343381589041;
0.009616497987562938;
0.01;
0.01;
0.01;
0.01;
0.01;
0.01;
0.009729708684089605;
0.009502885562962141;
0.009318436149380894;
0.009171442932983064;
0.009051270754143475;
0.008947483068198363;
0.00885204548848592;
0.008761414859845528;
0.008669257843807746;
0.00858335679762523;
0.00850911671531597;
0.008448254496094567;
0.008400053974155774;
0.008363439638319883;
0.00833701777801932;
0.008320015118229709;
0.008311620298505766;
0.008311620298505766;
0.008986910114619115;
0.008986910114619115;
0.008998282110652763;
0.009021816186198685;
0.009058714922675548;
0.009111283481011754;
0.009182578898369214;
0.009277149795748727;
0.009400748080005279;
0.009560370040602947;
0.009761548222746897;
0.01;
0.01;
0.01;
0.01;
0.01;
0.01;
0.01;
0.00977627143089333;
0.009602183811888721;
0.009475580019730784;
0.009377419831553989;
0.009291745143120573;
0.00920697553461081;
0.00912650562755562;
0.009023769916685777;
0.008927949575012657;
0.008849595801181031;
0.008788704435783105;
0.008742714824382871;
0.00870877458886184;
0.00868496235932086;
0.00866973066399616;
0.00866239149735223;
0.00866239149735223;
0.009251677713756365;
0.009251677713756365;
0.009260839880107938;
0.009279648485676436;
0.009309346259998507;
0.009351657949328164;
0.009409370975906838;
0.009486125813460478;
0.009586740301461897;
0.00971559330214866;
0.00986929746394964;
0.01;
0.01;
0.01;
0.01;
0.01;
0.01;
0.01;
0.01;
0.009838357130173359;
0.009751231928428231;
0.009690929771044817;
0.009635040994594642;
0.009557391935986283;
0.009513779524765124;
0.009371077647364516;
0.00925496503381479;
0.009172245191231469;
0.00911411908674583;
0.009072902082355618;
0.009043832364676383;
0.009023865283382643;
0.009011395206262176;
0.009005343635741828;
0.009005343635741828;
0.00950710823415747;
0.00950710823415747;
0.009513411637200354;
0.009526482232986211;
0.009547057046431214;
0.009576536711178888;
0.00961687174794591;
0.00967117148796466;
0.009744329854466214;
0.009845928760202842;
0.01;
0.01;
0.01;
0.01;
0.01;
0.01;
0.01;
0.01;
0.01;
0.01;
0.01;
0.01;
0.01;
0.009873730282440086;
0.01;
0.00969173065250978;
0.0095483464503982;
0.009470207866725673;
0.009422318927329046;
0.009390832073535589;
0.009369441908480169;
0.00935515084850722;
0.009346272756760055;
0.009342055919489028;
0.009342055919489028;
0.0;
0.01;
0.01;
0.01;
0.01;
0.01;
0.01;
0.01;
0.01;
0.01;
0.01;
0.01;
0.01;
0.01;
0.01;
0.01;
0.01;
0.01;
0.01;
0.01;
0.01;
0.01;
0.01;
0.01;
0.01;
0.01;
0.01;
0.01;
0.01;
0.01;
0.01;
0.01;
0.01;
0.01;
0.0;

</solute>
<solute name="ai2" unit="g.L-1" resolution="8.0" nI="33" nJ="33" nK="1">
0.0;
0.0;
0.0;
0.0;
0.0;
0.0;
0.0;
0.0;
0.0;
0.0;
0.0;
0.0;
0.0;
0.0;
0.0;
0.0;
0.0;
0.0;
0.0;
0.0;
0.0;
0.0;
0.0;
0.0;
0.0;
0.0;
0.0;
0.0;
0.0;
0.0;
0.0;
0.0;
0.0;
0.0;
0.0;
0.0;
0.0;
0.0;
0.0;
0.0;
0.0;
0.0;
0.0;
0.0;
0.0;
0.0;
0.0;
0.0;
0.0;
0.0;
0.0;
0.0;
0.0;
0.0;
0.0;
0.0;
0.0;
0.0;
0.0;
0.0;
0.0;
0.0;
0.0;
0.0;
0.0;
0.0;
0.0;
0.0;
0.0;
0.0;
0.0;
0.0;
0.0;
0.0;
0.0;
0.0;
0.0;
0.0;
0.0;
0.0;
0.0;
0.0;
0.0;
0.0;
0.0;
0.0;
0.0;
0.0;
0.0;
0.0;
0.0;
0.0;
0.0;
0.0;
0.0;
0.0;
0.0;
0.0;
0.0;
0.0;
0.0;
0.0;
0.0;
0.0;
0.0;
0.0;
0.0;
0.0;
0.0;
0.0;
0.0;
0.0;
0.0;
0.0;
0.0;
0.0;
0.0;
0.0;
0.0;
0.0;
0.0;
0.0;
0.0;
0.0;
0.0;
0.0;
0.0;
0.0;
0.0;
0.0;
0.0;
0.0;
0.0;
0.0;
0.0;
0.0;
0.0;
0.0;
0.0;
0.0;
0.0;
0.0;
0.0;
0.0;
0.0;
0.0;
0.0;
0.0;
0.0;
0.0;
0.0;
0.0;
0.0;
0.0;
0.0;
0.0;
0.0;
0.0;
0.0;
0.0;
0.0;
0.0;
0.0;
0.0;
0.0;
0.0;
0.0;
0.0;
0.0;
0.0;
0.0;
0.0;
0.0;
0.0;
0.0;
0.0;
0.0;
0.0;
0.0;
0.0;
0.0;
0.0;
0.0;
0.0;
0.0;
0.0;
0.0;
0.0;
0.0;
0.0;
0.0;
0.0;
0.0;
0.0;
0.0;
0.0;
0.0;
0.0;
0.0;
0.0;
0.0;
0.0;
0.0;
0.0;
0.0;
0.0;
0.0;
0.0;
0.0;
0.0;
0.0;
0.0;
0.0;
0.0;
0.0;
0.0;
0.0;
0.0;
0.0;
0.0;
0.0;
0.0;
0.0;
0.0;
0.0;
0.0;
0.0;
0.0;
0.0;
0.0;
0.0;
0.0;
0.0;
0.0;
0.0;
0.0;
0.0;
0.0;
0.0;
0.0;
0.0;
0.0;
0.0;
0.0;
0.0;
0.0;
0.0;
0.0;
0.0;
0.0;
0.0;
0.0;
0.0;
0.0;
0.0;
0.0;
0.0;
0.0;
0.0;
0.0;
0.0;
0.0;
0.0;
0.0;
0.0;
0.0;
0.0;
0.0;
0.0;
0.0;
0.0;
0.0;
0.0;
0.0;
0.0;
0.0;
0.0;
0.0;
0.0;
0.0;
0.0;
0.0;
0.0;
0.0;
0.0;
0.0;
0.0;
0.0;
0.0;
0.0;
0.0;
0.0;
0.0;
0.0;
0.0;
0.0;
0.0;
0.0;
0.0;
0.0;
0.0;
0.0;
0.0;
0.0;
0.0;
0.0;
0.0;
0.0;
0.0;
0.0;
0.0;
0.0;
0.0;
0.0;
0.0;
0.0;
0.0;
0.0;
0.0;
0.0;
0.0;
0.0;
0.0;
0.0;
0.0;
0.0;
0.0;
0.0;
0.0;
0.0;
0.0;
0.0;
0.0;
0.0;
0.0;
0.0;
0.0;
0.0;
0.0;
0.0;
0.0;
0.0;
0.0;
0.0;
0.0;
0.0;
0.0;
0.0;
0.0;
0.0;
0.0;
0.0;
0.0;
0.0;
0.0;
0.0;
0.0;
0.0;
0.0;
0.0;
0.0;
0.0;
0.0;
0.0;
0.0;
0.0;
0.0;
0.0;
0.0;
0.0;
0.0;
0.0;
0.0;
0.0;
0.0;
0.0;
0.0;
0.0;
0.0;
0.0;
0.0;
0.0;
0.0;
0.0;
0.0;
0.0;
0.0;
0.0;
0.0;
0.0;
0.0;
0.0;
0.0;
0.0;
0.0;
0.0;
0.0;
0.0;
0.0;
0.0;
0.0;
0.0;
0.0;
0.0;
0.0;
0.0;
0.0;
0.0;
0.0;
0.0;
0.0;
0.0;
0.0;
0.0;
0.0;
0.0;
0.0;
0.0;
0.0;
0.0;
0.0;
0.0;
0.0;
0.0;
0.0;
0.0;
0.0;
0.0;
0.0;
0.0;
0.0;
0.0;
0.0;
0.0;
0.0;
0.0;
0.0;
0.0;
0.0;
0.0;
0.0;
0.0;
0.0;
0.0;
0.0;
0.0;
0.0;
0.0;
0.0;
0.0;
0.0;
0.0;
0.0;
0.0;
0.0;
0.0;
0.0;
0.0;
0.0;
0.0;
0.0;
0.0;
0.0;
0.0;
0.0;
0.0;
0.0;
0.0;
0.0;
0.0;
0.0;
0.0;
0.0;
0.0;
0.0;
0.0;
0.0;
0.0;
0.0;
0.0;
0.0;
0.0;
0.0;
0.0;
0.0;
0.0;
0.0;
0.0;
0.0;
0.0;
0.0;
0.0;
0.0;
0.0;
0.0;
0.0;
0.0;
0.0;
0.0;
0.0;
0.0;
0.0;
0.0;
0.0;
0.0;
0.0;
0.0;
0.0;
0.0;
0.0;
0.0;
0.0;
0.0;
0.0;
0.0;
0.0;
0.0;
0.0;
0.0;
0.0;
0.0;
0.0;
0.0;
0.0;
0.0;
0.0;
0.0;
0.0;
0.0;
0.0;
0.0;
0.0;
0.0;
0.0;
0.0;
0.0;
0.0;
0.0;
0.0;
0.0;
0.0;
0.0;
0.0;
0.0;
0.0;
0.0;
0.0;
0.0;
0.0;
0.0;
0.0;
0.0;
0.0;
0.0;
0.0;
0.0;
0.0;
0.0;
0.0;
0.0;
0.0;
0.0;
0.0;
0.0;
0.0;
0.0;
0.0;
0.0;
0.0;
0.0;
0.0;
0.0;
0.0;
0.0;
0.0;
0.0;
0.0;
0.0;
0.0;
0.0;
0.0;
0.0;
0.0;
0.0;
0.0;
0.0;
0.0;
0.0;
0.0;
0.0;
0.0;
0.0;
0.0;
0.0;
0.0;
0.0;
0.0;
0.0;
0.0;
0.0;
0.0;
0.0;
0.0;
0.0;
0.0;
0.0;
0.0;
0.0;
0.0;
0.0;
0.0;
0.0;
0.0;
0.0;
0.0;
0.0;
0.0;
0.0;
0.0;
0.0;
0.0;
0.0;
0.0;
0.0;
0.0;
0.0;
0.0;
0.0;
0.0;
0.0;
0.0;
0.0;
0.0;
0.0;
0.0;
0.0;
0.0;
0.0;
0.0;
0.0;
0.0;
0.0;
0.0;
0.0;
0.0;
0.0;
0.0;
0.0;
0.0;
0.0;
0.0;
0.0;
0.0;
0.0;
0.0;
0.0;
0.0;
0.0;
0.0;
0.0;
0.0;
0.0;
0.0;
0.0;
0.0;
0.0;
0.0;
0.0;
0.0;
0.0;
0.0;
0.0;
0.0;
0.0;
0.0;
0.0;
0.0;
0.0;
0.0;
0.0;
0.0;
0.0;
0.0;
0.0;
0.0;
0.0;
0.0;
0.0;
0.0;
0.0;
0.0;
0.0;
0.0;
0.0;
0.0;
0.0;
0.0;
0.0;
0.0;
0.0;
0.0;
0.0;
0.0;
0.0;
0.0;
0.0;
0.0;
0.0;
0.0;
0.0;
0.0;
0.0;
0.0;
0.0;
0.0;
0.0;
0.0;
0.0;
0.0;
0.0;
0.0;
0.0;
0.0;
0.0;
0.0;
0.0;
0.0;
0.0;
0.0;
0.0;
0.0;
0.0;
0.0;
0.0;
0.0;
0.0;
0.0;
0.0;
0.0;
0.0;
0.0;
0.0;
0.0;
0.0;
0.0;
0.0;
0.0;
0.0;
0.0;
0.0;
0.0;
0.0;
0.0;
0.0;
0.0;
0.0;
0.0;
0.0;
0.0;
0.0;
0.0;
0.0;
0.0;
0.0;
0.0;
0.0;
0.0;
0.0;
0.0;
0.0;
0.0;
0.0;
0.0;
0.0;
0.0;
0.0;
0.0;
0.0;
0.0;
0.0;
0.0;
0.0;
0.0;
0.0;
0.0;
0.0;
0.0;
0.0;
0.0;
0.0;
0.0;
0.0;
0.0;
0.0;
0.0;
0.0;
0.0;
0.0;
0.0;
0.0;
0.0;
0.0;
0.0;
0.0;
0.0;
0.0;
0.0;
0.0;
0.0;
0.0;
0.0;
0.0;
0.0;
0.0;
0.0;
0.0;
0.0;
0.0;
0.0;
0.0;
0.0;
0.0;
0.0;
0.0;
0.0;
0.0;
0.0;
0.0;
0.0;
0.0;
0.0;
0.0;
0.0;
0.0;
0.0;
0.0;
0.0;
0.0;
0.0;
0.0;
0.0;
0.0;
0.0;
0.0;
0.0;
0.0;
0.0;
0.0;
0.0;
0.0;
0.0;
0.0;
0.0;
0.0;
0.0;
0.0;
0.0;
0.0;
0.0;
0.0;
0.0;
0.0;
0.0;
0.0;
0.0;
0.0;
0.0;
0.0;
0.0;
0.0;
0.0;
0.0;
0.0;
0.0;
0.0;
0.0;
0.0;
0.0;
0.0;
0.0;
0.0;
0.0;
0.0;
0.0;
0.0;
0.0;
0.0;
0.0;
0.0;
0.0;
0.0;
0.0;
0.0;
0.0;
0.0;
0.0;
0.0;
0.0;
0.0;
0.0;
0.0;
0.0;
0.0;
0.0;
0.0;
0.0;
0.0;
0.0;
0.0;
0.0;
0.0;
0.0;
0.0;
0.0;
0.0;
0.0;
0.0;
0.0;
0.0;
0.0;
0.0;
0.0;
0.0;
0.0;
0.0;
0.0;
0.0;
0.0;
0.0;
0.0;
0.0;
0.0;
0.0;
0.0;
0.0;
0.0;
0.0;
0.0;
0.0;
0.0;
0.0;
0.0;
0.0;
0.0;
0.0;
0.0;
0.0;
0.0;
0.0;
0.0;
0.0;
0.0;
0.0;
0.0;
0.0;
0.0;
0.0;
0.0;
0.0;
0.0;
0.0;
0.0;
0.0;
0.0;
0.0;
0.0;
0.0;
0.0;
0.0;
0.0;
0.0;
0.0;
0.0;
0.0;
0.0;
0.0;
0.0;
0.0;
0.0;
0.0;
0.0;
0.0;
0.0;
0.0;
0.0;
0.0;
0.0;
0.0;
0.0;
0.0;
0.0;
0.0;
0.0;
0.0;
0.0;
0.0;
0.0;
0.0;
0.0;
0.0;
0.0;
0.0;
0.0;
0.0;
0.0;
0.0;
0.0;
0.0;
0.0;
0.0;
0.0;
0.0;
0.0;
0.0;
0.0;
0.0;
0.0;
0.0;
0.0;
0.0;
0.0;
0.0;
0.0;
0.0;
0.0;
0.0;
0.0;
0.0;
0.0;
0.0;
0.0;
0.0;
0.0;
0.0;
0.0;
0.0;
0.0;
0.0;
0.0;
0.0;
0.0;
0.0;
0.0;
0.0;
0.0;
0.0;
0.0;
0.0;
0.0;
0.0;
0.0;
0.0;
0.0;
0.0;
0.0;
0.0;
0.0;
0.0;
0.0;
0.0;
0.0;
0.0;
0.0;
0.0;
0.0;
0.0;
0.0;
0.0;
0.0;
0.0;
0.0;
0.0;
0.0;
0.0;
0.0;
0.0;
0.0;
0.0;
0.0;
0.0;
0.0;
0.0;
0.0;
0.0;
0.0;
0.0;
0.0;
0.0;
0.0;
0.0;
0.0;
0.0;
0.0;
0.0;
0.0;
0.0;
0.0;
0.0;
0.0;
0.0;
0.0;
0.0;
0.0;
0.0;
0.0;
0.0;
0.0;
0.0;
0.0;
0.0;
0.0;
0.0;
0.0;
0.0;
0.0;
0.0;
0.0;
0.0;
0.0;
0.0;
0.0;
0.0;
0.0;
0.0;
0.0;
0.0;
0.0;
0.0;
0.0;
0.0;
0.0;
0.0;
0.0;
0.0;
0.0;
0.0;
0.0;
0.0;
0.0;
0.0;
0.0;
0.0;
0.0;
0.0;
0.0;
0.0;
0.0;
0.0;
0.0;
0.0;
0.0;
0.0;
0.0;
0.0;
0.0;
0.0;
0.0;
0.0;
0.0;
0.0;
0.0;
0.0;
0.0;
0.0;
0.0;
0.0;
0.0;
0.0;
0.0;
0.0;
0.0;
0.0;
0.0;
0.0;
0.0;
0.0;
0.0;
0.0;
0.0;
0.0;
0.0;
0.0;
0.0;
0.0;
0.0;
0.0;
0.0;
0.0;
0.0;
0.0;
0.0;
0.0;
0.0;
0.0;
0.0;
0.0;
0.0;
0.0;
0.0;
0.0;
0.0;
0.0;
0.0;
0.0;
0.0;
0.0;
0.0;
0.0;
0.0;
0.0;
0.0;
0.0;
0.0;
0.0;
0.0;
0.0;
0.0;
0.0;
0.0;
0.0;
0.0;
0.0;
0.0;
0.0;
0.0;

</solute>
<solute name="pressure" unit="g.L-1" resolution="8.0" nI="33" nJ="33" nK="1">
0.0;
2.317005583067755;
2.386964889654461;
2.4351444164895164;
2.5428432458781494;
2.608895850564297;
2.7219334592388447;
2.7737581929295834;
2.8658768923697853;
2.8847017689305052;
2.939772449603532;
2.9165287800760598;
2.930420209945902;
2.8721690536952353;
2.857639516982861;
2.77998065555283;
2.7478335233391795;
2.656305146423074;
2.604437516669886;
2.490044805210958;
2.4048016032758803;
2.259185615119495;
2.1441824807461827;
1.988519944708303;
1.878077182991754;
1.749595571618227;
1.6728633325134579;
1.581190581630868;
1.534892180382883;
1.4693380609021633;
1.4458071663046934;
1.3979960834761294;
1.389449989173268;
1.3517580643811367;
0.0;
2.317005583067755;
2.317005583067755;
2.386964889654461;
2.4351444164895164;
2.5428432458781494;
2.608895850564297;
2.7219334592388447;
2.7737581929295834;
2.8658768923697853;
2.8847017689305052;
2.939772449603532;
2.9165287800760598;
2.930420209945902;
2.8721690536952353;
2.857639516982861;
2.77998065555283;
2.7478335233391795;
2.656305146423074;
2.604437516669886;
2.490044805210958;
2.4048016032758803;
2.259185615119495;
2.1441824807461827;
1.988519944708303;
1.878077182991754;
1.749595571618227;
1.6728633325134579;
1.581190581630868;
1.534892180382883;
1.4693380609021633;
1.4458071663046934;
1.3979960834761294;
1.389449989173268;
1.3517580643811367;
1.3517580643811367;
2.4996188993883095;
2.4996188993883095;
2.53801215839152;
2.6445356045199295;
2.7262535216820156;
2.859983792337987;
2.9399441465619374;
3.05857155846602;
3.1068998840046986;
3.1885541720813713;
3.1897103896586128;
3.2205170212882517;
3.1717778433138752;
3.1604747063111316;
3.0838687271709384;
3.052156830794387;
2.962304835559056;
2.916496065722559;
2.812096556190709;
2.7381153454062064;
2.597471350449684;
2.477428215430757;
2.3019887609465663;
2.162171341693466;
1.999231214039695;
1.893600871249185;
1.7825467533684032;
1.7226524338173759;
1.6477338661973193;
1.6178364988634257;
1.5672820843708117;
1.5583039795294422;
1.5196635243124634;
1.5185779422423582;
1.5185779422423582;
2.7650031934698145;
2.7650031934698145;
2.86929655547779;
2.9654081352552226;
3.132689013893387;
3.262161140394571;
3.425463991643186;
3.520382807306264;
3.6428898510055685;
3.684619330194763;
3.7456765475839604;
3.715659879613407;
3.7053229769464915;
3.6222327477468648;
3.582368117925395;
3.485821693144211;
3.43370594951595;
3.3328374279304014;
3.2707552960513486;
3.143050472185135;
3.0256588313755413;
2.831772416516082;
2.650147556243942;
2.4291638091561594;
2.2607805690498797;
2.1047427009305335;
2.0252679353852354;
1.9403075383163924;
1.902453849114624;
1.8511727784195189;
1.847395357239441;
1.817250019602764;
1.8253493108752965;
1.7918455246477873;
1.7918455246477873;
3.141383034575081;
3.141383034575081;
3.277120413710768;
3.4535496913006303;
3.662287457052558;
3.9064528528167304;
4.076922791985033;
4.260091957876644;
4.365022327857226;
4.481696258871257;
4.500073569381495;
4.5090178677530295;
4.41361591697799;
4.345225375473442;
4.235997845999036;
4.166522913889053;
4.046466988265733;
3.984370557484593;
3.8831353313334596;
3.7912985918149325;
3.610620472220334;
3.399457959384736;
3.1067609675535217;
2.8362357870756645;
2.561856315346854;
2.4118865461814996;
2.3268144374722572;
2.2861143701702873;
2.2313129396362514;
2.232447528323392;
2.2233541648136965;
2.2589427230105343;
2.249487315034113;
2.2674867293621754;
2.2674867293621754;
3.4265610311532013;
3.4265610311532013;
3.6257027568657088;
3.9506159492019233;
4.378831746160037;
4.704398787297449;
4.980697978162686;
5.16868936111066;
5.364426851646405;
5.4739248610187605;
5.556262125686544;
5.489502666466698;
5.341764614239101;
5.164740357666748;
5.104540689334786;
4.969614916960679;
4.835727639930432;
4.745220794420369;
4.718521797698214;
4.600822943881866;
4.438662155434985;
4.111168205632537;
3.7156212123180588;
3.2788739325524796;
2.855561047510673;
2.6201608682217135;
2.707605022809399;
2.6902665220059627;
2.676438947654691;
2.687155419044518;
2.771689169805002;
2.824980000180267;
2.8995562867198563;
2.892608367514699;
2.892608367514699;
3.3393880986751907;
3.3393880986751907;
3.4145506343614063;
4.190509655547302;
5.181719044235204;
5.732648304359194;
6.020406850187391;
6.296508607402926;
6.510973611195808;
6.72746987577298;
6.799404161436862;
6.678025846010103;
6.150386459618551;
5.8274492843559065;
5.988687404479803;
5.863796815608636;
5.418785420056918;
5.5001663802775855;
5.64206435631294;
5.593367757740266;
5.453896669389498;
5.008958441066774;
4.323554731997588;
3.676987908984363;
2.653999626846167;
2.325557540820368;
3.0585282079787537;
3.159611841786036;
3.1094538902895255;
3.2429151436887595;
3.4224149014904075;
3.6228144806884677;
3.7241079477410737;
3.8021615411803458;
3.8021615411803458;
0.0;
0.0;
0.0;
3.6088342466640038;
5.920452626722433;
6.727292801347951;
7.040086313616464;
7.276357254894979;
7.623456582022278;
7.972022995208075;
8.022606717254808;
7.631028132059702;
6.322327940608666;
5.1601021942213166;
6.422284873417734;
6.29541559727834;
5.102804887409595;
5.372096852831689;
6.1754119145277;
6.351569333594564;
6.611056691721458;
5.759537869029103;
4.411619600832155;
3.5909015393111643;
0.0;
0.0;
3.0173912595518955;
3.298298308389504;
3.112212240335646;
3.68503571043221;
4.249428795774503;
4.604515591552775;
4.870209084839928;
4.950470025190529;
4.950470025190529;
0.0;
0.0;
0.0;
0.0;
5.9475930972514535;
7.019165918943868;
6.375356167959123;
6.835940380147147;
6.589071564512314;
7.461475851883879;
7.43180435251123;
6.057991405770271;
4.547412553667201;
0.0;
3.637583694377006;
4.291018488817014;
0.0;
0.0;
3.68522299411501;
5.308933478993036;
6.307376425282578;
4.806365202552998;
0.0;
1.901866337655258;
0.0;
0.0;
0.0;
0.0;
0.0;
3.650581367758245;
5.188804437984897;
5.91995051072541;
6.303390824689645;
6.517613872790953;
6.517613872790953;
0.0;
0.0;
0.0;
0.0;
4.647510992719358;
4.228533154102935;
0.0;
0.0;
0.0;
0.0;
0.0;
0.0;
0.0;
0.0;
0.0;
0.0;
0.0;
0.0;
0.0;
0.0;
0.0;
0.0;
0.0;
0.0;
0.0;
0.0;
0.0;
0.0;
0.0;
3.189798956015237;
6.28556065006559;
7.539585071912607;
8.206627418682832;
8.472645676632606;
8.472645676632606;
0.0;
0.0;
0.0;
0.0;
3.2702694860833073;
0.0;
0.0;
0.0;
0.0;
0.0;
0.0;
0.0;
0.0;
0.0;
0.0;
0.0;
0.0;
0.0;
0.0;
0.0;
0.0;
0.0;
0.0;
0.0;
0.0;
0.0;
0.0;
0.0;
0.0;
0.0;
6.552558810510009;
9.51748766928782;
10.5548484755896;
11.024026359093444;
11.024026359093444;
0.0;
0.0;
0.0;
0.0;
2.3908191037684774;
0.0;
0.0;
0.0;
0.0;
0.0;
0.0;
0.0;
0.0;
0.0;
0.0;
0.0;
0.0;
0.0;
0.0;
0.0;
0.0;
0.0;
0.0;
0.0;
0.0;
0.0;
0.0;
0.0;
0.0;
0.0;
5.113064135883037;
11.635752796063866;
13.464873106539233;
14.150752337833358;
14.150752337833358;
0.0;
0.0;
0.0;
0.0;
0.0;
0.0;
0.0;
0.0;
0.0;
0.0;
0.0;
0.0;
0.0;
0.0;
0.0;
0.0;
0.0;
0.0;
0.0;
0.0;
0.0;
0.0;
0.0;
0.0;
0.0;
0.0;
0.0;
0.0;
0.0;
0.0;
0.0;
12.830845747798485;
16.629619817449367;
17.912730088018364;
17.912730088018364;
0.0;
0.0;
0.0;
0.0;
0.0;
0.0;
0.0;
0.0;
0.0;
0.0;
0.0;
0.0;
0.0;
0.0;
0.0;
0.0;
0.0;
0.0;
0.0;
0.0;
0.0;
0.0;
0.0;
0.0;
0.0;
0.0;
0.0;
0.0;
0.0;
0.0;
0.0;
11.086755710291133;
19.551134117236966;
21.2075983049111;
21.2075983049111;
0.0;
0.0;
0.0;
0.0;
0.0;
0.0;
0.0;
0.0;
0.0;
0.0;
0.0;
0.0;
0.0;
0.0;
0.0;
0.0;
0.0;
0.0;
0.0;
0.0;
0.0;
0.0;
0.0;
0.0;
0.0;
0.0;
0.0;
0.0;
0.0;
0.0;
0.0;
8.207984163685726;
12.636607795850804;
19.7349981144647;
19.7349981144647;
0.0;
0.0;
0.0;
0.0;
0.0;
0.0;
0.0;
0.0;
0.0;
0.0;
0.0;
0.0;
0.0;
0.0;
0.0;
0.0;
0.0;
0.0;
0.0;
0.0;
0.0;
0.0;
0.0;
0.0;
0.0;
0.0;
0.0;
0.0;
0.0;
0.0;
0.0;
0.0;
0.0;
8.694492381746484;
8.694492381746484;
0.0;
0.0;
0.0;
0.0;
0.0;
0.0;
0.0;
0.0;
0.0;
0.0;
0.0;
0.0;
0.0;
0.0;
0.0;
0.0;
0.0;
0.0;
0.0;
0.0;
0.0;
0.0;
0.0;
0.0;
0.0;
0.0;
0.0;
0.0;
0.0;
0.0;
0.0;
0.0;
0.0;
0.0;
0.0;
0.0;
0.0;
0.0;
0.0;
0.0;
0.0;
0.0;
0.0;
0.0;
0.0;
0.0;
0.0;
0.0;
0.0;
0.0;
0.0;
0.0;
0.0;
0.0;
0.0;
0.0;
0.0;
0.0;
0.0;
0.0;
0.0;
0.0;
0.0;
0.0;
0.0;
0.0;
0.0;
0.0;
0.0;
0.0;
0.0;
0.0;
0.0;
0.0;
0.0;
0.0;
0.0;
0.0;
0.0;
0.0;
0.0;
0.0;
0.0;
0.0;
0.0;
0.0;
0.0;
0.0;
0.0;
0.0;
0.0;
0.0;
0.0;
0.0;
0.0;
0.0;
0.0;
0.0;
0.0;
0.0;
0.0;
0.0;
0.0;
0.0;
0.0;
0.0;
0.0;
0.0;
0.0;
0.0;
0.0;
0.0;
0.0;
0.0;
0.0;
0.0;
0.0;
0.0;
0.0;
0.0;
0.0;
0.0;
0.0;
0.0;
0.0;
0.0;
0.0;
0.0;
0.0;
0.0;
0.0;
0.0;
0.0;
0.0;
0.0;
0.0;
0.0;
0.0;
0.0;
0.0;
0.0;
0.0;
0.0;
0.0;
0.0;
0.0;
0.0;
0.0;
0.0;
0.0;
0.0;
0.0;
0.0;
0.0;
0.0;
0.0;
0.0;
0.0;
0.0;
0.0;
0.0;
0.0;
0.0;
0.0;
0.0;
0.0;
0.0;
0.0;
0.0;
0.0;
0.0;
0.0;
0.0;
0.0;
0.0;
0.0;
0.0;
0.0;
0.0;
0.0;
0.0;
0.0;
0.0;
0.0;
0.0;
0.0;
0.0;
0.0;
0.0;
0.0;
0.0;
0.0;
0.0;
0.0;
0.0;
0.0;
0.0;
0.0;
0.0;
0.0;
0.0;
0.0;
0.0;
0.0;
0.0;
0.0;
0.0;
0.0;
0.0;
0.0;
0.0;
0.0;
0.0;
0.0;
0.0;
0.0;
0.0;
0.0;
0.0;
0.0;
0.0;
0.0;
0.0;
0.0;
0.0;
0.0;
0.0;
0.0;
0.0;
0.0;
0.0;
0.0;
0.0;
0.0;
0.0;
0.0;
0.0;
0.0;
0.0;
0.0;
0.0;
0.0;
0.0;
0.0;
0.0;
0.0;
0.0;
0.0;
0.0;
0.0;
0.0;
0.0;
0.0;
0.0;
0.0;
0.0;
0.0;
0.0;
0.0;
0.0;
0.0;
0.0;
0.0;
0.0;
0.0;
0.0;
0.0;
0.0;
0.0;
0.0;
0.0;
0.0;
0.0;
0.0;
0.0;
0.0;
0.0;
0.0;
0.0;
0.0;
0.0;
0.0;
0.0;
0.0;
0.0;
0.0;
0.0;
0.0;
0.0;
0.0;
0.0;
0.0;
0.0;
0.0;
0.0;
0.0;
0.0;
0.0;
0.0;
0.0;
0.0;
0.0;
0.0;
0.0;
0.0;
0.0;
0.0;
0.0;
0.0;
0.0;
0.0;
0.0;
0.0;
0.0;
0.0;
0.0;
0.0;
0.0;
0.0;
0.0;
0.0;
0.0;
0.0;
0.0;
0.0;
0.0;
0.0;
0.0;
0.0;
0.0;
0.0;
0.0;
0.0;
0.0;
0.0;
0.0;
0.0;
0.0;
0.0;
0.0;
0.0;
0.0;
0.0;
0.0;
0.0;
0.0;
0.0;
0.0;
0.0;
0.0;
0.0;
0.0;
0.0;
0.0;
0.0;
0.0;
0.0;
0.0;
0.0;
0.0;
0.0;
0.0;
0.0;
0.0;
0.0;
0.0;
0.0;
0.0;
0.0;
0.0;
0.0;
0.0;
0.0;
0.0;
0.0;
0.0;
0.0;
0.0;
0.0;
0.0;
0.0;
0.0;
0.0;
0.0;
0.0;
0.0;
0.0;
0.0;
0.0;
0.0;
0.0;
0.0;
0.0;
0.0;
0.0;
0.0;
0.0;
0.0;
0.0;
0.0;
0.0;
0.0;
0.0;
0.0;
0.0;
0.0;
0.0;
0.0;
0.0;
0.0;
0.0;
0.0;
0.0;
0.0;
0.0;
0.0;
0.0;
0.0;
0.0;
0.0;
0.0;
0.0;
0.0;
0.0;
0.0;
0.0;
0.0;
0.0;
0.0;
0.0;
0.0;
0.0;
0.0;
0.0;
0.0;
0.0;
0.0;
0.0;
0.0;
0.0;
0.0;
0.0;
0.0;
0.0;
0.0;
0.0;
0.0;
0.0;
0.0;
0.0;
0.0;
0.0;
0.0;
0.0;
0.0;
0.0;
0.0;
0.0;
0.0;
0.0;
0.0;
0.0;
0.0;
0.0;
0.0;
0.0;
0.0;
0.0;
0.0;
0.0;
0.0;
0.0;
0.0;
0.0;
0.0;
0.0;
0.0;
0.0;
0.0;
0.0;
0.0;
0.0;
0.0;
0.0;
0.0;
0.0;
0.0;
0.0;
0.0;
0.0;
0.0;
0.0;
0.0;
0.0;
0.0;
0.0;
0.0;
0.0;
0.0;
0.0;
0.0;
0.0;
0.0;
0.0;
0.0;
0.0;
0.0;
0.0;
0.0;
0.0;
0.0;
0.0;
0.0;
0.0;
0.0;
0.0;
0.0;
0.0;
0.0;
0.0;
0.0;
0.0;
0.0;
0.0;
0.0;
0.0;
0.0;
0.0;
0.0;
0.0;
0.0;
0.0;
0.0;
0.0;
0.0;
0.0;
0.0;
0.0;
0.0;
0.0;
0.0;
0.0;
0.0;
0.0;
0.0;
0.0;
0.0;
0.0;
0.0;
0.0;
0.0;
0.0;
0.0;
0.0;
0.0;
0.0;
0.0;
0.0;
0.0;
0.0;
0.0;
0.0;
0.0;
0.0;
0.0;
0.0;
0.0;
0.0;
0.0;
0.0;
0.0;
0.0;
0.0;
0.0;
0.0;
0.0;
0.0;
0.0;
0.0;
0.0;
0.0;
0.0;
0.0;
0.0;
0.0;
0.0;
0.0;
0.0;
0.0;
0.0;
0.0;
0.0;
0.0;
0.0;
0.0;
0.0;
0.0;
0.0;
0.0;
0.0;
0.0;
0.0;
0.0;
0.0;
0.0;
0.0;
0.0;
0.0;
0.0;
0.0;
0.0;
0.0;
0.0;
0.0;
0.0;
0.0;
0.0;
0.0;
0.0;
0.0;
0.0;
0.0;
0.0;
0.0;
0.0;
0.0;
0.0;
0.0;
0.0;
0.0;
0.0;
0.0;
0.0;
0.0;
0.0;
0.0;
0.0;
0.0;
0.0;
0.0;
0.0;
0.0;
0.0;
0.0;
0.0;
0.0;
0.0;
0.0;
0.0;
0.0;
0.0;
0.0;
0.0;
0.0;
0.0;
0.0;
0.0;
0.0;
0.0;
0.0;
0.0;
0.0;
0.0;
0.0;
0.0;

</solute>
<solute name="MyGrowthHeterotrophs-rate" unit="g.L-1" resolution="8.0" nI="33" nJ="33" nK="1">
0.0;
0.0;
0.0;
0.0;
0.0;
0.0;
0.0;
0.0;
0.0;
0.0;
0.0;
0.0;
0.0;
0.0;
0.0;
0.0;
0.0;
0.0;
0.0;
0.0;
0.0;
0.0;
0.0;
0.0;
0.0;
0.0;
0.0;
0.0;
0.0;
0.0;
0.0;
0.0;
0.0;
0.0;
0.0;
0.0;
5.624917388431237E-8;
3.25249778503188E-8;
1.736069630669183E-8;
4.891424830751196E-9;
2.4941903337535244E-9;
1.6134240512840652E-9;
1.1948457499582916E-9;
8.107633465398539E-10;
1.457523386474167E-9;
3.2504282040483846E-9;
1.0041906575176323E-8;
1.55647224482324E-8;
2.553797879721569E-8;
1.3124742378500503E-8;
8.127278224932074E-9;
4.9096665809458E-9;
4.761636892651964E-9;
3.0553482527766212E-9;
1.9811963652194485E-9;
1.5769415425929223E-9;
2.2195070735800277E-9;
9.059689934006866E-9;
1.5012759531744993E-8;
3.335577598423095E-8;
6.580106973401634E-8;
2.586353875388872E-8;
7.016377841758517E-9;
3.0227843312049567E-9;
9.991204669415179E-10;
1.9445912152874997E-10;
6.289408558337765E-11;
1.4239737653509971E-11;
7.535561118779E-12;
0.0;
0.0;
1.9200352379436393E-7;
2.0326205570540972E-7;
1.0502234547886425E-7;
4.631554835394069E-8;
1.5775612449005664E-8;
1.0007958455114135E-8;
9.313462899356087E-9;
1.0584304499636039E-8;
1.0369713126431624E-8;
2.596336423429688E-8;
5.77540731896073E-8;
1.4662505327947753E-7;
8.978939539957376E-8;
7.737524257268884E-8;
5.812977905718945E-8;
4.871290728898793E-8;
3.730993543882818E-8;
2.2787448952023443E-8;
2.381858676712274E-8;
1.261072117842515E-8;
1.7706958684969135E-8;
3.5452673798748236E-8;
9.597083167289433E-8;
2.939673047134121E-7;
3.076404866828399E-7;
1.3796941450456186E-7;
4.869230615004212E-8;
2.9700363871352905E-8;
6.653450014794815E-9;
2.027108594089762E-9;
4.434758020528321E-10;
1.3443761939494178E-10;
4.124554615799273E-11;
0.0;
0.0;
2.0744221057934607E-6;
1.7115378806844857E-6;
9.855799730751083E-7;
3.3997146818175794E-7;
1.5542581014390407E-7;
1.0896329732811458E-7;
6.623342961926345E-8;
7.275816393369617E-8;
9.078590302291454E-8;
1.3266399700184396E-7;
5.795443071601018E-7;
7.045913506622734E-7;
8.185855909069108E-7;
5.993727039677697E-7;
3.8778271384572904E-7;
4.950814289307091E-7;
3.362092344348109E-7;
2.1523685829621518E-7;
1.5603599560534585E-7;
1.738752682190081E-7;
1.8098650774775146E-7;
3.686327388337131E-7;
8.704338870236959E-7;
2.666334588018797E-6;
1.1206454020441733E-6;
1.2122781349856295E-6;
3.2800703360193567E-7;
1.6215185248106037E-7;
4.627967822175292E-8;
1.2864475804762945E-8;
2.9342149950929668E-9;
9.057464450233984E-10;
2.4806715639362117E-10;
0.0;
0.0;
1.2198806516200302E-5;
2.057976479721094E-5;
6.73746760896223E-6;
2.821040147125294E-6;
1.0065496823744386E-6;
8.751567316474214E-7;
9.687461199157132E-7;
7.6693741993164E-7;
5.263014355092687E-7;
9.607548951576635E-7;
4.575180686017898E-6;
9.142688969351371E-6;
1.0061869129098548E-5;
4.220197192913459E-6;
3.935417870589515E-6;
6.457741227549646E-6;
3.364103728562664E-6;
1.8400847736928095E-6;
1.1569329994989988E-6;
9.738286630437274E-7;
1.269891618393436E-6;
2.419511234014404E-6;
6.257393410317014E-6;
7.227738674583248E-6;
1.493840289894976E-5;
6.050633129001567E-6;
1.539978817790816E-6;
1.2260120568772139E-6;
5.143617511000646E-7;
1.0870943889257751E-7;
2.6655790217905373E-8;
3.842928603072316E-9;
9.003121452298025E-10;
0.0;
0.0;
1.0393523031833592E-4;
1.236500064941658E-4;
7.326052070653286E-5;
1.6422756791076027E-5;
9.611218149404934E-6;
8.123102553601268E-6;
6.070437601498469E-6;
4.809009224539263E-6;
6.11675801020063E-6;
1.0286785795128659E-5;
3.157658432991235E-5;
6.318644551168287E-5;
7.370564496684312E-5;
3.201920515162167E-5;
2.7755975873034536E-5;
4.679853849291484E-5;
3.4357548132816056E-5;
1.4182995561052128E-5;
1.0615485247871667E-5;
9.873934073906732E-6;
1.1921932199416036E-5;
2.476349947121675E-5;
3.374417925977943E-5;
8.216120411242016E-5;
4.378362863783686E-5;
3.548979575483914E-5;
1.5813383946509422E-5;
1.2046737255491492E-5;
3.8272308188039E-6;
9.121158794233528E-7;
1.7365236839937565E-7;
3.4037036943189875E-8;
8.489181079646432E-9;
0.0;
0.0;
7.586817959051913E-4;
5.236968143204676E-4;
1.2830106208379065E-4;
1.1488079797879865E-4;
7.388058737958691E-5;
5.1512159536718476E-5;
8.806011020322477E-5;
2.4797551180349104E-5;
4.44108616518685E-5;
9.28327882562108E-5;
1.8804853642818002E-4;
1.299219631195475E-4;
2.6364264370203945E-4;
1.6115246579261842E-4;
2.1382974600856055E-4;
1.1013458188480798E-4;
1.794418413360641E-4;
1.5643454633118204E-4;
9.145449063276325E-5;
7.029249496998588E-5;
1.0347885280537439E-4;
1.1645296312740272E-4;
2.0655441685249785E-4;
3.1729982012768527E-4;
2.080650598825784E-4;
2.3758973173764188E-4;
1.0696697816807039E-4;
9.851268677547527E-5;
3.141303881033691E-5;
6.3384835740289815E-6;
1.1431565576899335E-6;
2.458542413444661E-7;
4.6309167723659315E-8;
0.0;
0.0;
0.0;
0.0;
7.879344584716864E-4;
6.83862421497433E-4;
3.845635578897548E-4;
4.459222500256194E-4;
3.899022324142247E-4;
5.228132661938281E-4;
5.329941329230054E-4;
6.009447447601321E-4;
7.082026153864305E-4;
4.082634522907823E-4;
4.5862963960723697E-4;
0.001105593729732402;
0.0011040509852686155;
7.749107355392693E-4;
9.481483016573002E-4;
0.0011438612852664584;
4.536813350155866E-4;
6.212071539656246E-4;
3.2117844845591783E-4;
9.215739766393006E-4;
8.975669384548779E-4;
0.0;
0.0;
0.0010700966129336968;
7.364006834877345E-4;
6.475877675121514E-4;
1.4435069220707582E-4;
3.916141238918761E-5;
4.96158103374532E-6;
1.1733605220109818E-6;
2.2752364949459902E-7;
0.0;
0.0;
0.0;
0.0;
0.0;
0.0010520606201015119;
9.305358938069865E-4;
0.0010643645073262176;
0.0015364058770650645;
0.0011758225881223262;
0.0016097036882555906;
0.0018268642077342262;
7.865402636101935E-4;
7.822183245114702E-4;
0.0;
7.95440265914597E-4;
0.0015110164698234323;
0.0;
0.0;
7.724089452509041E-4;
0.0013532357121704;
0.0016456483244417241;
0.0012213289297735182;
0.0;
7.588224408352481E-4;
0.0;
0.0;
0.0;
0.0;
0.0;
4.890315109569528E-4;
1.9443260550714212E-4;
3.543822434315724E-5;
3.923588806702026E-6;
8.470808086988228E-7;
0.0;
0.0;
0.0;
0.0;
0.0;
0.0017748736703974766;
0.0017804155983621034;
0.0;
0.0;
0.0;
0.0;
0.0;
0.0;
0.0;
0.0;
0.0;
0.0;
0.0;
0.0;
0.0;
0.0;
0.0;
0.0;
0.0;
0.0;
0.0;
0.0;
0.0;
0.0;
0.0;
5.528201441379076E-4;
8.365345273985413E-4;
7.964635936066991E-5;
1.146442528836928E-5;
2.418332767733678E-6;
0.0;
0.0;
0.0;
0.0;
0.0;
0.0010559868784192849;
0.0;
0.0;
0.0;
0.0;
0.0;
0.0;
0.0;
0.0;
0.0;
0.0;
0.0;
0.0;
0.0;
0.0;
0.0;
0.0;
0.0;
0.0;
0.0;
0.0;
0.0;
0.0;
0.0;
0.0;
0.0;
0.0016809465796459172;
4.347846597610571E-4;
7.47633891157988E-5;
1.2468579824659094E-5;
0.0;
0.0;
0.0;
0.0;
0.0;
0.0011465265460696092;
0.0;
0.0;
0.0;
0.0;
0.0;
0.0;
0.0;
0.0;
0.0;
0.0;
0.0;
0.0;
0.0;
0.0;
0.0;
0.0;
0.0;
0.0;
0.0;
0.0;
0.0;
0.0;
0.0;
0.0;
0.0;
8.095790039632042E-4;
0.0011992147389322094;
2.6219132511331187E-4;
8.481213022520512E-5;
0.0;
0.0;
0.0;
0.0;
0.0;
0.0;
0.0;
0.0;
0.0;
0.0;
0.0;
0.0;
0.0;
0.0;
0.0;
0.0;
0.0;
0.0;
0.0;
0.0;
0.0;
0.0;
0.0;
0.0;
0.0;
0.0;
0.0;
0.0;
0.0;
0.0;
0.0;
0.0;
0.0019044030431869243;
5.495088189350226E-4;
4.5031634059219966E-4;
0.0;
0.0;
0.0;
0.0;
0.0;
0.0;
0.0;
0.0;
0.0;
0.0;
0.0;
0.0;
0.0;
0.0;
0.0;
0.0;
0.0;
0.0;
0.0;
0.0;
0.0;
0.0;
0.0;
0.0;
0.0;
0.0;
0.0;
0.0;
0.0;
0.0;
0.0;
0.0;
9.38132807001993E-4;
0.002281651232738819;
0.0012237605911265804;
0.0;
0.0;
0.0;
0.0;
0.0;
0.0;
0.0;
0.0;
0.0;
0.0;
0.0;
0.0;
0.0;
0.0;
0.0;
0.0;
0.0;
0.0;
0.0;
0.0;
0.0;
0.0;
0.0;
0.0;
0.0;
0.0;
0.0;
0.0;
0.0;
0.0;
0.0;
0.0;
0.003287100487958502;
0.0034812369584499977;
0.0037092380159659153;
0.0;
0.0;
0.0;
0.0;
0.0;
0.0;
0.0;
0.0;
0.0;
0.0;
0.0;
0.0;
0.0;
0.0;
0.0;
0.0;
0.0;
0.0;
0.0;
0.0;
0.0;
0.0;
0.0;
0.0;
0.0;
0.0;
0.0;
0.0;
0.0;
0.0;
0.0;
0.0;
0.0;
0.0;
0.002312532328270751;
0.0;
0.0;
0.0;
0.0;
0.0;
0.0;
0.0;
0.0;
0.0;
0.0;
0.0;
0.0;
0.0;
0.0;
0.0;
0.0;
0.0;
0.0;
0.0;
0.0;
0.0;
0.0;
0.0;
0.0;
0.0;
0.0;
0.0;
0.0;
0.0;
0.0;
0.0;
0.0;
0.0;
0.0;
0.0;
0.0;
0.0;
0.0;
0.0;
0.0;
0.0;
0.0;
0.0;
0.0;
0.0;
0.0;
0.0;
0.0;
0.0;
0.0;
0.0;
0.0;
0.0;
0.0;
0.0;
0.0;
0.0;
0.0;
0.0;
0.0;
0.0;
0.0;
0.0;
0.0;
0.0;
0.0;
0.0;
0.0;
0.0;
0.0;
0.0;
0.0;
0.0;
0.0;
0.0;
0.0;
0.0;
0.0;
0.0;
0.0;
0.0;
0.0;
0.0;
0.0;
0.0;
0.0;
0.0;
0.0;
0.0;
0.0;
0.0;
0.0;
0.0;
0.0;
0.0;
0.0;
0.0;
0.0;
0.0;
0.0;
0.0;
0.0;
0.0;
0.0;
0.0;
0.0;
0.0;
0.0;
0.0;
0.0;
0.0;
0.0;
0.0;
0.0;
0.0;
0.0;
0.0;
0.0;
0.0;
0.0;
0.0;
0.0;
0.0;
0.0;
0.0;
0.0;
0.0;
0.0;
0.0;
0.0;
0.0;
0.0;
0.0;
0.0;
0.0;
0.0;
0.0;
0.0;
0.0;
0.0;
0.0;
0.0;
0.0;
0.0;
0.0;
0.0;
0.0;
0.0;
0.0;
0.0;
0.0;
0.0;
0.0;
0.0;
0.0;
0.0;
0.0;
0.0;
0.0;
0.0;
0.0;
0.0;
0.0;
0.0;
0.0;
0.0;
0.0;
0.0;
0.0;
0.0;
0.0;
0.0;
0.0;
0.0;
0.0;
0.0;
0.0;
0.0;
0.0;
0.0;
0.0;
0.0;
0.0;
0.0;
0.0;
0.0;
0.0;
0.0;
0.0;
0.0;
0.0;
0.0;
0.0;
0.0;
0.0;
0.0;
0.0;
0.0;
0.0;
0.0;
0.0;
0.0;
0.0;
0.0;
0.0;
0.0;
0.0;
0.0;
0.0;
0.0;
0.0;
0.0;
0.0;
0.0;
0.0;
0.0;
0.0;
0.0;
0.0;
0.0;
0.0;
0.0;
0.0;
0.0;
0.0;
0.0;
0.0;
0.0;
0.0;
0.0;
0.0;
0.0;
0.0;
0.0;
0.0;
0.0;
0.0;
0.0;
0.0;
0.0;
0.0;
0.0;
0.0;
0.0;
0.0;
0.0;
0.0;
0.0;
0.0;
0.0;
0.0;
0.0;
0.0;
0.0;
0.0;
0.0;
0.0;
0.0;
0.0;
0.0;
0.0;
0.0;
0.0;
0.0;
0.0;
0.0;
0.0;
0.0;
0.0;
0.0;
0.0;
0.0;
0.0;
0.0;
0.0;
0.0;
0.0;
0.0;
0.0;
0.0;
0.0;
0.0;
0.0;
0.0;
0.0;
0.0;
0.0;
0.0;
0.0;
0.0;
0.0;
0.0;
0.0;
0.0;
0.0;
0.0;
0.0;
0.0;
0.0;
0.0;
0.0;
0.0;
0.0;
0.0;
0.0;
0.0;
0.0;
0.0;
0.0;
0.0;
0.0;
0.0;
0.0;
0.0;
0.0;
0.0;
0.0;
0.0;
0.0;
0.0;
0.0;
0.0;
0.0;
0.0;
0.0;
0.0;
0.0;
0.0;
0.0;
0.0;
0.0;
0.0;
0.0;
0.0;
0.0;
0.0;
0.0;
0.0;
0.0;
0.0;
0.0;
0.0;
0.0;
0.0;
0.0;
0.0;
0.0;
0.0;
0.0;
0.0;
0.0;
0.0;
0.0;
0.0;
0.0;
0.0;
0.0;
0.0;
0.0;
0.0;
0.0;
0.0;
0.0;
0.0;
0.0;
0.0;
0.0;
0.0;
0.0;
0.0;
0.0;
0.0;
0.0;
0.0;
0.0;
0.0;
0.0;
0.0;
0.0;
0.0;
0.0;
0.0;
0.0;
0.0;
0.0;
0.0;
0.0;
0.0;
0.0;
0.0;
0.0;
0.0;
0.0;
0.0;
0.0;
0.0;
0.0;
0.0;
0.0;
0.0;
0.0;
0.0;
0.0;
0.0;
0.0;
0.0;
0.0;
0.0;
0.0;
0.0;
0.0;
0.0;
0.0;
0.0;
0.0;
0.0;
0.0;
0.0;
0.0;
0.0;
0.0;
0.0;
0.0;
0.0;
0.0;
0.0;
0.0;
0.0;
0.0;
0.0;
0.0;
0.0;
0.0;
0.0;
0.0;
0.0;
0.0;
0.0;
0.0;
0.0;
0.0;
0.0;
0.0;
0.0;
0.0;
0.0;
0.0;
0.0;
0.0;
0.0;
0.0;
0.0;
0.0;
0.0;
0.0;
0.0;
0.0;
0.0;
0.0;
0.0;
0.0;
0.0;
0.0;
0.0;
0.0;
0.0;
0.0;
0.0;
0.0;
0.0;
0.0;
0.0;
0.0;
0.0;
0.0;
0.0;
0.0;
0.0;
0.0;
0.0;
0.0;
0.0;
0.0;
0.0;
0.0;
0.0;
0.0;
0.0;
0.0;
0.0;
0.0;
0.0;
0.0;
0.0;
0.0;
0.0;
0.0;
0.0;
0.0;
0.0;
0.0;
0.0;
0.0;
0.0;
0.0;
0.0;
0.0;
0.0;
0.0;
0.0;
0.0;
0.0;
0.0;
0.0;
0.0;
0.0;
0.0;
0.0;
0.0;
0.0;
0.0;
0.0;
0.0;
0.0;
0.0;
0.0;
0.0;
0.0;
0.0;
0.0;
0.0;
0.0;
0.0;
0.0;
0.0;
0.0;
0.0;
0.0;
0.0;
0.0;
0.0;
0.0;
0.0;
0.0;
0.0;
0.0;
0.0;
0.0;
0.0;
0.0;
0.0;
0.0;
0.0;
0.0;
0.0;
0.0;
0.0;
0.0;
0.0;
0.0;
0.0;
0.0;
0.0;
0.0;
0.0;
0.0;
0.0;
0.0;
0.0;
0.0;
0.0;
0.0;
0.0;
0.0;
0.0;
0.0;
0.0;
0.0;
0.0;
0.0;
0.0;
0.0;
0.0;
0.0;
0.0;
0.0;
0.0;
0.0;
0.0;
0.0;
0.0;
0.0;
0.0;
0.0;
0.0;
0.0;
0.0;
0.0;
0.0;
0.0;
0.0;
0.0;
0.0;
0.0;
0.0;
0.0;
0.0;
0.0;
0.0;
0.0;
0.0;
0.0;
0.0;
0.0;
0.0;
0.0;
0.0;
0.0;
0.0;
0.0;
0.0;
0.0;
0.0;
0.0;
0.0;
0.0;
0.0;
0.0;
0.0;
0.0;
0.0;
0.0;
0.0;
0.0;
0.0;
0.0;
0.0;
0.0;
0.0;
0.0;
0.0;
0.0;
0.0;
0.0;
0.0;
0.0;
0.0;
0.0;
0.0;
0.0;
0.0;
0.0;
0.0;
0.0;
0.0;
0.0;
0.0;
0.0;
0.0;
0.0;
0.0;
0.0;
0.0;
0.0;
0.0;
0.0;

</solute>
<solute name="ai2Growth-rate" unit="g.L-1" resolution="8.0" nI="33" nJ="33" nK="1">
0.0;
0.0;
0.0;
0.0;
0.0;
0.0;
0.0;
0.0;
0.0;
0.0;
0.0;
0.0;
0.0;
0.0;
0.0;
0.0;
0.0;
0.0;
0.0;
0.0;
0.0;
0.0;
0.0;
0.0;
0.0;
0.0;
0.0;
0.0;
0.0;
0.0;
0.0;
0.0;
0.0;
0.0;
0.0;
0.0;
0.0;
0.0;
0.0;
0.0;
0.0;
0.0;
0.0;
0.0;
0.0;
0.0;
0.0;
0.0;
0.0;
0.0;
0.0;
0.0;
0.0;
0.0;
0.0;
0.0;
0.0;
0.0;
0.0;
0.0;
0.0;
0.0;
0.0;
0.0;
0.0;
0.0;
0.0;
0.0;
0.0;
0.0;
0.0;
0.0;
0.0;
0.0;
0.0;
0.0;
0.0;
0.0;
0.0;
0.0;
0.0;
0.0;
0.0;
0.0;
0.0;
0.0;
0.0;
0.0;
0.0;
0.0;
0.0;
0.0;
0.0;
0.0;
0.0;
0.0;
0.0;
0.0;
0.0;
0.0;
0.0;
0.0;
0.0;
0.0;
0.0;
0.0;
0.0;
0.0;
0.0;
0.0;
0.0;
0.0;
0.0;
0.0;
0.0;
0.0;
0.0;
0.0;
0.0;
0.0;
0.0;
0.0;
0.0;
0.0;
0.0;
0.0;
0.0;
0.0;
0.0;
0.0;
0.0;
0.0;
0.0;
0.0;
0.0;
0.0;
0.0;
0.0;
0.0;
0.0;
0.0;
0.0;
0.0;
0.0;
0.0;
0.0;
0.0;
0.0;
0.0;
0.0;
0.0;
0.0;
0.0;
0.0;
0.0;
0.0;
0.0;
0.0;
0.0;
0.0;
0.0;
0.0;
0.0;
0.0;
0.0;
0.0;
0.0;
0.0;
0.0;
0.0;
0.0;
0.0;
0.0;
0.0;
0.0;
0.0;
0.0;
0.0;
0.0;
0.0;
0.0;
0.0;
0.0;
0.0;
0.0;
0.0;
0.0;
0.0;
0.0;
0.0;
0.0;
0.0;
0.0;
0.0;
0.0;
0.0;
0.0;
0.0;
0.0;
0.0;
0.0;
0.0;
0.0;
0.0;
0.0;
0.0;
0.0;
0.0;
0.0;
0.0;
0.0;
0.0;
0.0;
0.0;
0.0;
0.0;
0.0;
0.0;
0.0;
0.0;
0.0;
0.0;
0.0;
0.0;
0.0;
0.0;
0.0;
0.0;
0.0;
0.0;
0.0;
0.0;
0.0;
0.0;
0.0;
0.0;
0.0;
0.0;
0.0;
0.0;
0.0;
0.0;
0.0;
0.0;
0.0;
0.0;
0.0;
0.0;
0.0;
0.0;
0.0;
0.0;
0.0;
0.0;
0.0;
0.0;
0.0;
0.0;
0.0;
0.0;
0.0;
0.0;
0.0;
0.0;
0.0;
0.0;
0.0;
0.0;
0.0;
0.0;
0.0;
0.0;
0.0;
0.0;
0.0;
0.0;
0.0;
0.0;
0.0;
0.0;
0.0;
0.0;
0.0;
0.0;
0.0;
0.0;
0.0;
0.0;
0.0;
0.0;
0.0;
0.0;
0.0;
0.0;
0.0;
0.0;
0.0;
0.0;
0.0;
0.0;
0.0;
0.0;
0.0;
0.0;
0.0;
0.0;
0.0;
0.0;
0.0;
0.0;
0.0;
0.0;
0.0;
0.0;
0.0;
0.0;
0.0;
0.0;
0.0;
0.0;
0.0;
0.0;
0.0;
0.0;
0.0;
0.0;
0.0;
0.0;
0.0;
0.0;
0.0;
0.0;
0.0;
0.0;
0.0;
0.0;
0.0;
0.0;
0.0;
0.0;
0.0;
0.0;
0.0;
0.0;
0.0;
0.0;
0.0;
0.0;
0.0;
0.0;
0.0;
0.0;
0.0;
0.0;
0.0;
0.0;
0.0;
0.0;
0.0;
0.0;
0.0;
0.0;
0.0;
0.0;
0.0;
0.0;
0.0;
0.0;
0.0;
0.0;
0.0;
0.0;
0.0;
0.0;
0.0;
0.0;
0.0;
0.0;
0.0;
0.0;
0.0;
0.0;
0.0;
0.0;
0.0;
0.0;
0.0;
0.0;
0.0;
0.0;
0.0;
0.0;
0.0;
0.0;
0.0;
0.0;
0.0;
0.0;
0.0;
0.0;
0.0;
0.0;
0.0;
0.0;
0.0;
0.0;
0.0;
0.0;
0.0;
0.0;
0.0;
0.0;
0.0;
0.0;
0.0;
0.0;
0.0;
0.0;
0.0;
0.0;
0.0;
0.0;
0.0;
0.0;
0.0;
0.0;
0.0;
0.0;
0.0;
0.0;
0.0;
0.0;
0.0;
0.0;
0.0;
0.0;
0.0;
0.0;
0.0;
0.0;
0.0;
0.0;
0.0;
0.0;
0.0;
0.0;
0.0;
0.0;
0.0;
0.0;
0.0;
0.0;
0.0;
0.0;
0.0;
0.0;
0.0;
0.0;
0.0;
0.0;
0.0;
0.0;
0.0;
0.0;
0.0;
0.0;
0.0;
0.0;
0.0;
0.0;
0.0;
0.0;
0.0;
0.0;
0.0;
0.0;
0.0;
0.0;
0.0;
0.0;
0.0;
0.0;
0.0;
0.0;
0.0;
0.0;
0.0;
0.0;
0.0;
0.0;
0.0;
0.0;
0.0;
0.0;
0.0;
0.0;
0.0;
0.0;
0.0;
0.0;
0.0;
0.0;
0.0;
0.0;
0.0;
0.0;
0.0;
0.0;
0.0;
0.0;
0.0;
0.0;
0.0;
0.0;
0.0;
0.0;
0.0;
0.0;
0.0;
0.0;
0.0;
0.0;
0.0;
0.0;
0.0;
0.0;
0.0;
0.0;
0.0;
0.0;
0.0;
0.0;
0.0;
0.0;
0.0;
0.0;
0.0;
0.0;
0.0;
0.0;
0.0;
0.0;
0.0;
0.0;
0.0;
0.0;
0.0;
0.0;
0.0;
0.0;
0.0;
0.0;
0.0;
0.0;
0.0;
0.0;
0.0;
0.0;
0.0;
0.0;
0.0;
0.0;
0.0;
0.0;
0.0;
0.0;
0.0;
0.0;
0.0;
0.0;
0.0;
0.0;
0.0;
0.0;
0.0;
0.0;
0.0;
0.0;
0.0;
0.0;
0.0;
0.0;
0.0;
0.0;
0.0;
0.0;
0.0;
0.0;
0.0;
0.0;
0.0;
0.0;
0.0;
0.0;
0.0;
0.0;
0.0;
0.0;
0.0;
0.0;
0.0;
0.0;
0.0;
0.0;
0.0;
0.0;
0.0;
0.0;
0.0;
0.0;
0.0;
0.0;
0.0;
0.0;
0.0;
0.0;
0.0;
0.0;
0.0;
0.0;
0.0;
0.0;
0.0;
0.0;
0.0;
0.0;
0.0;
0.0;
0.0;
0.0;
0.0;
0.0;
0.0;
0.0;
0.0;
0.0;
0.0;
0.0;
0.0;
0.0;
0.0;
0.0;
0.0;
0.0;
0.0;
0.0;
0.0;
0.0;
0.0;
0.0;
0.0;
0.0;
0.0;
0.0;
0.0;
0.0;
0.0;
0.0;
0.0;
0.0;
0.0;
0.0;
0.0;
0.0;
0.0;
0.0;
0.0;
0.0;
0.0;
0.0;
0.0;
0.0;
0.0;
0.0;
0.0;
0.0;
0.0;
0.0;
0.0;
0.0;
0.0;
0.0;
0.0;
0.0;
0.0;
0.0;
0.0;
0.0;
0.0;
0.0;
0.0;
0.0;
0.0;
0.0;
0.0;
0.0;
0.0;
0.0;
0.0;
0.0;
0.0;
0.0;
0.0;
0.0;
0.0;
0.0;
0.0;
0.0;
0.0;
0.0;
0.0;
0.0;
0.0;
0.0;
0.0;
0.0;
0.0;
0.0;
0.0;
0.0;
0.0;
0.0;
0.0;
0.0;
0.0;
0.0;
0.0;
0.0;
0.0;
0.0;
0.0;
0.0;
0.0;
0.0;
0.0;
0.0;
0.0;
0.0;
0.0;
0.0;
0.0;
0.0;
0.0;
0.0;
0.0;
0.0;
0.0;
0.0;
0.0;
0.0;
0.0;
0.0;
0.0;
0.0;
0.0;
0.0;
0.0;
0.0;
0.0;
0.0;
0.0;
0.0;
0.0;
0.0;
0.0;
0.0;
0.0;
0.0;
0.0;
0.0;
0.0;
0.0;
0.0;
0.0;
0.0;
0.0;
0.0;
0.0;
0.0;
0.0;
0.0;
0.0;
0.0;
0.0;
0.0;
0.0;
0.0;
0.0;
0.0;
0.0;
0.0;
0.0;
0.0;
0.0;
0.0;
0.0;
0.0;
0.0;
0.0;
0.0;
0.0;
0.0;
0.0;
0.0;
0.0;
0.0;
0.0;
0.0;
0.0;
0.0;
0.0;
0.0;
0.0;
0.0;
0.0;
0.0;
0.0;
0.0;
0.0;
0.0;
0.0;
0.0;
0.0;
0.0;
0.0;
0.0;
0.0;
0.0;
0.0;
0.0;
0.0;
0.0;
0.0;
0.0;
0.0;
0.0;
0.0;
0.0;
0.0;
0.0;
0.0;
0.0;
0.0;
0.0;
0.0;
0.0;
0.0;
0.0;
0.0;
0.0;
0.0;
0.0;
0.0;
0.0;
0.0;
0.0;
0.0;
0.0;
0.0;
0.0;
0.0;
0.0;
0.0;
0.0;
0.0;
0.0;
0.0;
0.0;
0.0;
0.0;
0.0;
0.0;
0.0;
0.0;
0.0;
0.0;
0.0;
0.0;
0.0;
0.0;
0.0;
0.0;
0.0;
0.0;
0.0;
0.0;
0.0;
0.0;
0.0;
0.0;
0.0;
0.0;
0.0;
0.0;
0.0;
0.0;
0.0;
0.0;
0.0;
0.0;
0.0;
0.0;
0.0;
0.0;
0.0;
0.0;
0.0;
0.0;
0.0;
0.0;
0.0;
0.0;
0.0;
0.0;
0.0;
0.0;
0.0;
0.0;
0.0;
0.0;
0.0;
0.0;
0.0;
0.0;
0.0;
0.0;
0.0;
0.0;
0.0;
0.0;
0.0;
0.0;
0.0;
0.0;
0.0;
0.0;
0.0;
0.0;
0.0;
0.0;
0.0;
0.0;
0.0;
0.0;
0.0;
0.0;
0.0;
0.0;
0.0;
0.0;
0.0;
0.0;
0.0;
0.0;
0.0;
0.0;
0.0;
0.0;
0.0;
0.0;
0.0;
0.0;
0.0;
0.0;
0.0;
0.0;
0.0;
0.0;
0.0;
0.0;
0.0;
0.0;
0.0;
0.0;
0.0;
0.0;
0.0;
0.0;
0.0;
0.0;
0.0;
0.0;
0.0;
0.0;
0.0;
0.0;
0.0;
0.0;
0.0;
0.0;
0.0;
0.0;
0.0;
0.0;
0.0;
0.0;
0.0;
0.0;
0.0;
0.0;
0.0;
0.0;
0.0;
0.0;
0.0;
0.0;
0.0;
0.0;
0.0;
0.0;
0.0;
0.0;
0.0;
0.0;
0.0;
0.0;
0.0;
0.0;
0.0;
0.0;
0.0;
0.0;
0.0;
0.0;
0.0;
0.0;
0.0;
0.0;
0.0;
0.0;
0.0;
0.0;
0.0;
0.0;
0.0;
0.0;
0.0;
0.0;
0.0;
0.0;
0.0;
0.0;
0.0;
0.0;
0.0;
0.0;
0.0;
0.0;
0.0;
0.0;
0.0;
0.0;
0.0;
0.0;
0.0;
0.0;
0.0;
0.0;
0.0;
0.0;
0.0;
0.0;
0.0;
0.0;
0.0;
0.0;
0.0;
0.0;
0.0;
0.0;
0.0;
0.0;
0.0;
0.0;
0.0;
0.0;
0.0;
0.0;
0.0;
0.0;
0.0;
0.0;
0.0;
0.0;
0.0;
0.0;
0.0;
0.0;
0.0;
0.0;
0.0;
0.0;
0.0;
0.0;
0.0;
0.0;
0.0;
0.0;
0.0;
0.0;
0.0;
0.0;
0.0;
0.0;
0.0;
0.0;
0.0;
0.0;
0.0;
0.0;
0.0;
0.0;
0.0;
0.0;
0.0;
0.0;
0.0;
0.0;
0.0;
0.0;
0.0;
0.0;
0.0;
0.0;
0.0;
0.0;
0.0;
0.0;
0.0;
0.0;
0.0;
0.0;
0.0;
0.0;
0.0;
0.0;
0.0;
0.0;
0.0;
0.0;
0.0;
0.0;
0.0;
0.0;
0.0;
0.0;
0.0;
0.0;
0.0;
0.0;
0.0;
0.0;
0.0;
0.0;
0.0;
0.0;
0.0;
0.0;
0.0;
0.0;
0.0;
0.0;
0.0;
0.0;
0.0;
0.0;
0.0;
0.0;
0.0;
0.0;
0.0;
0.0;
0.0;
0.0;
0.0;
0.0;
0.0;
0.0;
0.0;
0.0;
0.0;
0.0;
0.0;
0.0;
0.0;
0.0;
0.0;
0.0;
0.0;
0.0;
0.0;
0.0;
0.0;
0.0;
0.0;
0.0;
0.0;
0.0;
0.0;
0.0;
0.0;
0.0;
0.0;
0.0;
0.0;
0.0;
0.0;
0.0;
0.0;
0.0;
0.0;
0.0;
0.0;
0.0;
0.0;
0.0;
0.0;
0.0;
0.0;
0.0;
0.0;
0.0;
0.0;
0.0;
0.0;

</solute>
<solute name="plank_dLuxS" unit="g.L-1" resolution="8.0" nI="33" nJ="33" nK="1">
0.0;
0.0;
0.0;
0.0;
0.0;
0.0;
0.0;
0.0;
0.0;
0.0;
0.0;
0.0;
0.0;
0.0;
0.0;
0.0;
0.0;
0.0;
0.0;
0.0;
0.0;
0.0;
0.0;
0.0;
0.0;
0.0;
0.0;
0.0;
0.0;
0.0;
0.0;
0.0;
0.0;
0.0;
0.0;
0.0;
0.0;
0.0;
0.0;
0.0;
0.0;
0.0;
0.0;
0.0;
0.0;
0.0;
0.0;
0.0;
0.0;
0.0;
0.0;
0.0;
0.0;
0.0;
0.0;
0.0;
0.0;
0.0;
0.0;
0.0;
0.0;
0.0;
0.0;
0.0;
0.0;
0.0;
0.0;
0.0;
0.0;
0.0;
0.0;
0.0;
0.0;
0.0;
0.0;
0.0;
0.0;
0.0;
0.0;
0.0;
0.0;
0.0;
0.0;
0.0;
0.0;
0.0;
0.0;
0.0;
0.0;
0.0;
0.0;
0.0;
0.0;
0.0;
0.0;
0.0;
0.0;
0.0;
0.0;
0.0;
0.0;
0.0;
0.0;
0.0;
0.0;
0.0;
21.45253661630915;
0.0;
0.0;
0.0;
0.0;
0.0;
0.0;
0.0;
0.0;
0.0;
0.0;
0.0;
0.0;
0.0;
0.0;
0.0;
0.0;
0.0;
0.0;
0.0;
0.0;
0.0;
0.0;
0.0;
0.0;
0.0;
0.0;
0.0;
0.0;
0.0;
0.0;
0.0;
0.0;
0.0;
0.0;
0.0;
0.0;
0.0;
0.0;
0.0;
0.0;
0.0;
0.0;
0.0;
0.0;
0.0;
0.0;
0.0;
0.0;
0.0;
0.0;
0.0;
0.0;
0.0;
0.0;
0.0;
0.0;
0.0;
0.0;
0.0;
0.0;
0.0;
0.0;
0.0;
0.0;
0.0;
0.0;
0.0;
0.0;
0.0;
0.0;
0.0;
0.0;
0.0;
0.0;
0.0;
0.0;
0.0;
0.0;
0.0;
0.0;
0.0;
0.0;
0.0;
0.0;
0.0;
0.0;
0.0;
0.0;
0.0;
0.0;
0.0;
0.0;
0.0;
0.0;
0.0;
0.0;
0.0;
0.0;
0.0;
0.0;
0.0;
0.0;
0.0;
0.0;
0.0;
0.0;
0.0;
0.0;
0.0;
0.0;
0.0;
0.0;
0.0;
0.0;
0.0;
0.0;
0.0;
0.0;
0.0;
0.0;
0.0;
0.0;
0.0;
0.0;
0.0;
0.0;
0.0;
0.0;
0.0;
0.0;
0.0;
0.0;
0.0;
0.0;
0.0;
0.0;
0.0;
0.0;
0.0;
0.0;
0.0;
0.0;
0.0;
0.0;
0.0;
0.0;
0.0;
0.0;
0.0;
0.0;
0.0;
0.0;
0.0;
0.0;
0.0;
0.0;
0.0;
0.0;
0.0;
0.0;
0.0;
0.0;
0.0;
0.0;
0.0;
0.0;
0.0;
0.0;
0.0;
0.0;
0.0;
0.0;
0.0;
0.0;
21.763106969645257;
0.0;
0.0;
0.0;
0.0;
0.0;
0.0;
0.0;
0.0;
0.0;
0.0;
0.0;
0.0;
0.0;
0.0;
0.0;
0.0;
0.0;
0.0;
0.0;
0.0;
0.0;
0.0;
0.0;
0.0;
0.0;
0.0;
0.0;
0.0;
0.0;
0.0;
0.0;
0.0;
0.0;
0.0;
0.0;
0.0;
0.0;
0.0;
0.0;
0.0;
0.0;
0.0;
0.0;
0.0;
0.0;
0.0;
0.0;
0.0;
0.0;
0.0;
0.0;
0.0;
0.0;
0.0;
0.0;
0.0;
0.0;
0.0;
0.0;
0.0;
0.0;
0.0;
0.0;
0.0;
0.0;
0.0;
0.0;
0.0;
0.0;
0.0;
0.0;
0.0;
0.0;
0.0;
0.0;
0.0;
0.0;
0.0;
0.0;
0.0;
0.0;
0.0;
0.0;
0.0;
0.0;
0.0;
0.0;
0.0;
0.0;
0.0;
0.0;
0.0;
0.0;
0.0;
0.0;
0.0;
0.0;
0.0;
0.0;
0.0;
0.0;
0.0;
0.0;
0.0;
0.0;
0.0;
0.0;
0.0;
0.0;
0.0;
0.0;
0.0;
0.0;
0.0;
0.0;
0.0;
0.0;
0.0;
0.0;
0.0;
0.0;
0.0;
0.0;
0.0;
0.0;
0.0;
0.0;
0.0;
0.0;
0.0;
0.0;
0.0;
0.0;
0.0;
0.0;
0.0;
0.0;
0.0;
0.0;
0.0;
23.8973280206634;
0.0;
0.0;
0.0;
0.0;
0.0;
0.0;
0.0;
0.0;
0.0;
0.0;
0.0;
0.0;
0.0;
0.0;
0.0;
0.0;
0.0;
0.0;
0.0;
0.0;
0.0;
0.0;
0.0;
0.0;
0.0;
0.0;
0.0;
0.0;
0.0;
0.0;
0.0;
0.0;
0.0;
0.0;
0.0;
0.0;
0.0;
0.0;
0.0;
0.0;
0.0;
0.0;
0.0;
0.0;
0.0;
0.0;
0.0;
0.0;
0.0;
0.0;
0.0;
0.0;
0.0;
0.0;
0.0;
0.0;
0.0;
0.0;
0.0;
0.0;
0.0;
0.0;
0.0;
0.0;
0.0;
0.0;
0.0;
0.0;
0.0;
0.0;
0.0;
0.0;
0.0;
0.0;
0.0;
0.0;
0.0;
0.0;
0.0;
0.0;
0.0;
0.0;
0.0;
0.0;
0.0;
0.0;
0.0;
0.0;
0.0;
0.0;
0.0;
0.0;
0.0;
0.0;
0.0;
11.041143669944661;
0.0;
0.0;
0.0;
0.0;
0.0;
0.0;
0.0;
0.0;
0.0;
0.0;
0.0;
0.0;
0.0;
0.0;
0.0;
0.0;
0.0;
0.0;
0.0;
0.0;
0.0;
0.0;
0.0;
0.0;
0.0;
0.0;
0.0;
0.0;
0.0;
0.0;
0.0;
0.0;
0.0;
0.0;
0.0;
0.0;
0.0;
0.0;
0.0;
0.0;
0.0;
0.0;
0.0;
0.0;
0.0;
0.0;
0.0;
0.0;
0.0;
0.0;
0.0;
0.0;
0.0;
15.45335086665615;
0.0;
0.0;
0.0;
0.0;
0.0;
0.0;
0.0;
0.0;
0.0;
0.0;
0.0;
0.0;
0.0;
0.0;
0.0;
0.0;
0.0;
0.0;
0.0;
0.0;
0.0;
0.0;
0.0;
0.0;
0.0;
0.0;
0.0;
0.0;
0.0;
0.0;
0.0;
0.0;
0.0;
0.0;
0.0;
0.0;
0.0;
0.0;
0.0;
0.0;
0.0;
0.0;
0.0;
0.0;
0.0;
0.0;
0.0;
0.0;
0.0;
0.0;
0.0;
0.0;
0.0;
0.0;
0.0;
0.0;
0.0;
0.0;
22.225394351946868;
0.0;
0.0;
17.167467469941844;
0.0;
0.0;
0.0;
0.0;
0.0;
0.0;
0.0;
0.0;
0.0;
0.0;
0.0;
0.0;
0.0;
0.0;
0.0;
0.0;
0.0;
0.0;
0.0;
0.0;
0.0;
0.0;
0.0;
0.0;
0.0;
0.0;
0.0;
0.0;
19.084744342528122;
0.0;
0.0;
0.0;
0.0;
0.0;
0.0;
0.0;
0.0;
0.0;
0.0;
0.0;
0.0;
0.0;
0.0;
0.0;
0.0;
0.0;
9.938135118324084;
0.0;
0.0;
0.0;
0.0;
0.0;
0.0;
0.0;
0.0;
0.0;
0.0;
0.0;
0.0;
0.0;
0.0;
0.0;
0.0;
0.0;
0.0;
0.0;
0.0;
0.0;
0.0;
0.0;
0.0;
0.0;
0.0;
0.0;
0.0;
0.0;
0.0;
0.0;
0.0;
0.0;
0.0;
0.0;
0.0;
0.0;
0.0;
0.0;
0.0;
0.0;
0.0;
0.0;
0.0;
0.0;
0.0;
0.0;
14.733680143525497;
0.0;
0.0;
0.0;
0.0;
0.0;
0.0;
0.0;
0.0;
0.0;
0.0;
0.0;
0.0;
0.0;
0.0;
0.0;
0.0;
0.0;
0.0;
0.0;
0.0;
0.0;
0.0;
0.0;
0.0;
0.0;
0.0;
0.0;
0.0;
0.0;
0.0;
0.0;
0.0;
0.0;
0.0;
0.0;
0.0;
0.0;
0.0;
0.0;
0.0;
0.0;
0.0;
0.0;
0.0;
0.0;
0.0;
18.628855633874764;
0.0;
0.0;
0.0;
0.0;
0.0;
0.0;
0.0;
0.0;
0.0;
0.0;
0.0;
0.0;
0.0;
0.0;
0.0;
0.0;
0.0;
0.0;
0.0;
0.0;
0.0;
0.0;
20.064482493668862;
0.0;
0.0;
0.0;
0.0;
0.0;
0.0;
0.0;
0.0;
0.0;
0.0;
0.0;
0.0;
0.0;
0.0;
0.0;
0.0;
0.0;
0.0;
0.0;
0.0;
0.0;
0.0;
0.0;
0.0;
0.0;
0.0;
0.0;
0.0;
0.0;
0.0;
0.0;
0.0;
0.0;
0.0;
0.0;
0.0;
0.0;
0.0;
0.0;
0.0;
0.0;
0.0;
0.0;
0.0;
0.0;
0.0;
0.0;
0.0;
0.0;
0.0;
0.0;
0.0;
0.0;
0.0;
0.0;
0.0;
0.0;
0.0;
0.0;
0.0;
0.0;
0.0;
0.0;
0.0;
0.0;
0.0;
0.0;
0.0;
0.0;
0.0;
0.0;
0.0;
0.0;
0.0;
0.0;
0.0;
0.0;
0.0;
0.0;
0.0;
0.0;
0.0;
0.0;
0.0;
0.0;
0.0;
0.0;
0.0;
0.0;
0.0;
0.0;
0.0;
0.0;
0.0;
0.0;
0.0;
0.0;
0.0;
0.0;
0.0;
0.0;
0.0;
0.0;
0.0;
0.0;
0.0;
0.0;
0.0;
0.0;
0.0;
0.0;
0.0;
0.0;
0.0;
0.0;
0.0;
0.0;
0.0;
0.0;
0.0;
0.0;
0.0;
0.0;
0.0;
0.0;
0.0;
0.0;
0.0;
0.0;
0.0;
0.0;
0.0;
0.0;
0.0;
0.0;
0.0;
0.0;
0.0;
0.0;
0.0;
0.0;
0.0;
0.0;
0.0;
0.0;
0.0;
0.0;
0.0;
0.0;
0.0;
0.0;
0.0;
0.0;
0.0;
0.0;
0.0;
0.0;
0.0;
0.0;
0.0;
0.0;
0.0;
0.0;
0.0;
0.0;
0.0;
0.0;
0.0;
0.0;
0.0;
0.0;
0.0;
0.0;
0.0;
0.0;
0.0;
0.0;
0.0;
0.0;
0.0;
0.0;
0.0;
0.0;
0.0;
0.0;
0.0;
0.0;
0.0;
0.0;
0.0;
0.0;
0.0;
0.0;
0.0;
0.0;
0.0;
0.0;
0.0;
0.0;
0.0;
0.0;
0.0;
0.0;
0.0;
0.0;
0.0;
0.0;
0.0;
0.0;
0.0;
0.0;
0.0;
0.0;
0.0;
0.0;
0.0;
0.0;
0.0;
0.0;
0.0;
0.0;
0.0;
0.0;
0.0;
0.0;
0.0;
0.0;
0.0;
0.0;
0.0;
0.0;
0.0;
0.0;
0.0;
0.0;
0.0;
0.0;
0.0;
0.0;
0.0;
0.0;
0.0;
0.0;
0.0;
0.0;
0.0;
0.0;
0.0;
0.0;
0.0;
0.0;
0.0;
0.0;
0.0;
0.0;
0.0;
0.0;
0.0;
0.0;
0.0;
0.0;
0.0;
0.0;
0.0;
0.0;
0.0;
0.0;
0.0;
0.0;
0.0;
0.0;
0.0;
0.0;
0.0;
0.0;
0.0;
0.0;
0.0;
0.0;
0.0;
0.0;
0.0;
0.0;
0.0;
0.0;
0.0;
0.0;
0.0;
0.0;
0.0;
0.0;
0.0;
0.0;
0.0;
0.0;
0.0;
0.0;
0.0;
0.0;
0.0;
0.0;
0.0;
0.0;
0.0;
0.0;
0.0;
0.0;
0.0;
0.0;
0.0;
0.0;
0.0;
0.0;
0.0;
0.0;
0.0;
0.0;
0.0;
0.0;
0.0;
0.0;
0.0;
0.0;
0.0;
0.0;
0.0;
0.0;
0.0;
0.0;
0.0;
0.0;
0.0;
0.0;
0.0;
0.0;
0.0;
0.0;
0.0;
0.0;
0.0;
0.0;
0.0;
0.0;
0.0;
0.0;
0.0;
0.0;
0.0;
0.0;
0.0;
0.0;
0.0;
0.0;
0.0;
0.0;
0.0;
0.0;
0.0;
0.0;
0.0;
0.0;
0.0;
0.0;
0.0;
0.0;
0.0;
0.0;
0.0;
0.0;
0.0;
0.0;
0.0;
0.0;
0.0;
0.0;
0.0;
0.0;
0.0;
0.0;
0.0;
0.0;
0.0;
0.0;
0.0;
0.0;
0.0;
0.0;
0.0;
0.0;
0.0;
0.0;
0.0;
0.0;
0.0;
0.0;
0.0;
0.0;
0.0;
0.0;
0.0;
0.0;
0.0;
0.0;
0.0;
0.0;
0.0;
0.0;
0.0;
0.0;
0.0;
0.0;
0.0;
0.0;
0.0;
0.0;
0.0;
0.0;
0.0;
0.0;
0.0;
0.0;
0.0;
0.0;
0.0;
0.0;

</solute>
<solute name="JoinedLuxS" unit="g.L-1" resolution="8.0" nI="33" nJ="33" nK="1">
0.0;
0.0;
0.0;
0.0;
0.0;
0.0;
0.0;
0.0;
0.0;
0.0;
0.0;
0.0;
0.0;
0.0;
0.0;
0.0;
0.0;
0.0;
0.0;
0.0;
0.0;
0.0;
0.0;
0.0;
0.0;
0.0;
0.0;
0.0;
0.0;
0.0;
0.0;
0.0;
0.0;
0.0;
0.0;
0.0;
64.64518329830311;
32.860782837170056;
0.0;
0.0;
0.0;
0.0;
0.0;
0.0;
0.0;
0.0;
0.0;
0.0;
0.0;
0.0;
0.0;
0.0;
0.0;
0.0;
0.0;
0.0;
0.0;
0.0;
0.0;
0.0;
0.0;
0.0;
0.0;
0.0;
35.44185851410919;
0.0;
0.0;
24.19443479381358;
89.13424700463514;
0.0;
0.0;
38.18891683100577;
36.55473727113254;
0.0;
0.0;
0.0;
0.0;
0.0;
0.0;
0.0;
0.0;
0.0;
0.0;
0.0;
0.0;
0.0;
0.0;
0.0;
0.0;
0.0;
0.0;
0.0;
0.0;
0.0;
0.0;
0.0;
0.0;
0.0;
0.0;
30.965776238058126;
47.14808199041704;
0.0;
101.2443276156544;
59.28548445749749;
0.0;
0.0;
72.82998152609557;
44.34152987550519;
0.0;
0.0;
0.0;
0.0;
0.0;
0.0;
0.0;
0.0;
0.0;
0.0;
0.0;
0.0;
0.0;
0.0;
0.0;
0.0;
0.0;
0.0;
0.0;
0.0;
0.0;
0.0;
0.0;
0.0;
0.0;
0.0;
36.32276884078978;
56.81795457457072;
0.0;
57.235157832254174;
42.69966303042207;
0.0;
0.0;
57.668818447933624;
64.26514842848117;
0.0;
14.902429824977206;
0.0;
0.0;
0.0;
0.0;
0.0;
0.0;
0.0;
0.0;
0.0;
0.0;
0.0;
0.0;
0.0;
0.0;
0.0;
0.0;
0.0;
0.0;
0.0;
0.0;
0.0;
0.0;
0.0;
0.0;
51.43951409723347;
92.72818135476216;
96.65449491461013;
54.4366247201322;
33.157862066205034;
0.0;
0.0;
55.64763849265443;
40.578544651092734;
0.0;
48.47241446143451;
51.57517470382371;
0.0;
0.0;
0.0;
0.0;
0.0;
0.0;
0.0;
0.0;
0.0;
0.0;
0.0;
0.0;
0.0;
0.0;
0.0;
0.0;
0.0;
0.0;
0.0;
0.0;
0.0;
0.0;
0.0;
40.99756144512316;
92.55247319882136;
100.80462001897602;
110.29191605360316;
94.49577657629447;
0.0;
0.0;
77.91240549159691;
45.794355755789326;
23.109084787526655;
103.82952322303603;
85.2829851617089;
0.0;
0.0;
0.0;
0.0;
0.0;
0.0;
0.0;
0.0;
0.0;
18.937832902798533;
0.0;
0.0;
0.0;
0.0;
0.0;
0.0;
0.0;
0.0;
0.0;
0.0;
0.0;
0.0;
0.0;
75.83303446860496;
90.75003266401814;
90.34515835988525;
120.10122147814018;
63.424928532348794;
0.0;
0.0;
0.0;
0.0;
51.25201225342117;
60.44390524121056;
47.107102006248;
0.0;
52.57181355412657;
96.36048191108763;
55.0906138413792;
0.0;
0.0;
0.0;
0.0;
58.604115967815325;
60.18392592851262;
0.0;
0.0;
0.0;
0.0;
0.0;
0.0;
0.0;
0.0;
0.0;
0.0;
0.0;
0.0;
0.0;
18.408856113545088;
116.57849788631692;
75.39989348654063;
80.5007190941367;
76.06709929982787;
0.0;
0.0;
0.0;
0.0;
0.0;
54.987664569823835;
47.9894455814149;
0.0;
37.30574903725784;
35.62345266974692;
35.090533776079006;
0.0;
0.0;
0.0;
0.0;
22.67138838300285;
44.59096120530408;
0.0;
0.0;
0.0;
0.0;
43.08172054600153;
0.0;
0.0;
0.0;
0.0;
0.0;
0.0;
0.0;
0.0;
48.370824117630804;
98.7185741611138;
102.14222088661343;
91.7593816255401;
55.549928776233074;
0.0;
0.0;
0.0;
0.0;
0.0;
27.09613445002251;
27.597986232481464;
0.0;
0.0;
0.0;
0.0;
0.0;
0.0;
0.0;
0.0;
0.0;
0.0;
0.0;
0.0;
0.0;
0.0;
0.0;
0.0;
0.0;
0.0;
0.0;
0.0;
0.0;
0.0;
0.0;
24.16725932545968;
89.78308686474688;
95.95724566647635;
71.43040223046998;
47.59732125945543;
0.0;
0.0;
0.0;
0.0;
0.0;
26.74071123508846;
0.0;
0.0;
0.0;
0.0;
0.0;
0.0;
0.0;
0.0;
0.0;
0.0;
0.0;
0.0;
0.0;
0.0;
0.0;
0.0;
0.0;
0.0;
0.0;
0.0;
0.0;
0.0;
0.0;
0.0;
0.0;
59.32601334520481;
114.74671508780798;
87.1799204157654;
62.49049650157569;
0.0;
0.0;
0.0;
0.0;
0.0;
25.590452689861028;
0.0;
0.0;
0.0;
0.0;
0.0;
0.0;
0.0;
0.0;
0.0;
0.0;
0.0;
0.0;
0.0;
0.0;
0.0;
0.0;
0.0;
0.0;
0.0;
0.0;
0.0;
0.0;
0.0;
0.0;
0.0;
13.123704098217148;
88.93966407463043;
67.8016293816953;
88.69562184211189;
0.0;
0.0;
0.0;
0.0;
0.0;
0.0;
0.0;
0.0;
0.0;
0.0;
0.0;
0.0;
0.0;
0.0;
0.0;
0.0;
0.0;
0.0;
0.0;
0.0;
0.0;
0.0;
0.0;
0.0;
0.0;
0.0;
0.0;
0.0;
0.0;
0.0;
0.0;
0.0;
87.55120952629314;
73.8962195936154;
94.54025936897142;
0.0;
0.0;
0.0;
0.0;
0.0;
0.0;
0.0;
0.0;
0.0;
0.0;
0.0;
0.0;
0.0;
0.0;
0.0;
0.0;
0.0;
0.0;
0.0;
0.0;
0.0;
0.0;
0.0;
0.0;
0.0;
0.0;
0.0;
0.0;
0.0;
0.0;
0.0;
0.0;
19.022911972054878;
87.5219996841989;
74.22715804915248;
0.0;
0.0;
0.0;
0.0;
0.0;
0.0;
0.0;
0.0;
0.0;
0.0;
0.0;
0.0;
0.0;
0.0;
0.0;
0.0;
0.0;
0.0;
0.0;
0.0;
0.0;
0.0;
0.0;
0.0;
0.0;
0.0;
0.0;
0.0;
0.0;
0.0;
0.0;
0.0;
38.76319278818297;
59.21615390103571;
67.4760986949809;
0.0;
0.0;
0.0;
0.0;
0.0;
0.0;
0.0;
0.0;
0.0;
0.0;
0.0;
0.0;
0.0;
0.0;
0.0;
0.0;
0.0;
0.0;
0.0;
0.0;
0.0;
0.0;
0.0;
0.0;
0.0;
0.0;
0.0;
0.0;
0.0;
0.0;
0.0;
0.0;
0.0;
0.0;
25.594540942988562;
0.0;
0.0;
0.0;
0.0;
0.0;
0.0;
0.0;
0.0;
0.0;
0.0;
0.0;
0.0;
0.0;
0.0;
0.0;
0.0;
0.0;
0.0;
0.0;
0.0;
0.0;
0.0;
0.0;
0.0;
0.0;
0.0;
0.0;
0.0;
0.0;
0.0;
0.0;
0.0;
0.0;
0.0;
0.0;
0.0;
0.0;
0.0;
0.0;
0.0;
0.0;
0.0;
0.0;
0.0;
0.0;
0.0;
0.0;
0.0;
0.0;
0.0;
0.0;
0.0;
0.0;
0.0;
0.0;
0.0;
0.0;
0.0;
0.0;
0.0;
0.0;
0.0;
0.0;
0.0;
0.0;
0.0;
0.0;
0.0;
0.0;
0.0;
0.0;
0.0;
0.0;
0.0;
0.0;
0.0;
0.0;
0.0;
0.0;
0.0;
0.0;
0.0;
0.0;
0.0;
0.0;
0.0;
0.0;
0.0;
0.0;
0.0;
0.0;
0.0;
0.0;
0.0;
0.0;
0.0;
0.0;
0.0;
0.0;
0.0;
0.0;
0.0;
0.0;
0.0;
0.0;
0.0;
0.0;
0.0;
0.0;
0.0;
0.0;
0.0;
0.0;
0.0;
0.0;
0.0;
0.0;
0.0;
0.0;
0.0;
0.0;
0.0;
0.0;
0.0;
0.0;
0.0;
0.0;
0.0;
0.0;
0.0;
0.0;
0.0;
0.0;
0.0;
0.0;
0.0;
0.0;
0.0;
0.0;
0.0;
0.0;
0.0;
0.0;
0.0;
0.0;
0.0;
0.0;
0.0;
0.0;
0.0;
0.0;
0.0;
0.0;
0.0;
0.0;
0.0;
0.0;
0.0;
0.0;
0.0;
0.0;
0.0;
0.0;
0.0;
0.0;
0.0;
0.0;
0.0;
0.0;
0.0;
0.0;
0.0;
0.0;
0.0;
0.0;
0.0;
0.0;
0.0;
0.0;
0.0;
0.0;
0.0;
0.0;
0.0;
0.0;
0.0;
0.0;
0.0;
0.0;
0.0;
0.0;
0.0;
0.0;
0.0;
0.0;
0.0;
0.0;
0.0;
0.0;
0.0;
0.0;
0.0;
0.0;
0.0;
0.0;
0.0;
0.0;
0.0;
0.0;
0.0;
0.0;
0.0;
0.0;
0.0;
0.0;
0.0;
0.0;
0.0;
0.0;
0.0;
0.0;
0.0;
0.0;
0.0;
0.0;
0.0;
0.0;
0.0;
0.0;
0.0;
0.0;
0.0;
0.0;
0.0;
0.0;
0.0;
0.0;
0.0;
0.0;
0.0;
0.0;
0.0;
0.0;
0.0;
0.0;
0.0;
0.0;
0.0;
0.0;
0.0;
0.0;
0.0;
0.0;
0.0;
0.0;
0.0;
0.0;
0.0;
0.0;
0.0;
0.0;
0.0;
0.0;
0.0;
0.0;
0.0;
0.0;
0.0;
0.0;
0.0;
0.0;
0.0;
0.0;
0.0;
0.0;
0.0;
0.0;
0.0;
0.0;
0.0;
0.0;
0.0;
0.0;
0.0;
0.0;
0.0;
0.0;
0.0;
0.0;
0.0;
0.0;
0.0;
0.0;
0.0;
0.0;
0.0;
0.0;
0.0;
0.0;
0.0;
0.0;
0.0;
0.0;
0.0;
0.0;
0.0;
0.0;
0.0;
0.0;
0.0;
0.0;
0.0;
0.0;
0.0;
0.0;
0.0;
0.0;
0.0;
0.0;
0.0;
0.0;
0.0;
0.0;
0.0;
0.0;
0.0;
0.0;
0.0;
0.0;
0.0;
0.0;
0.0;
0.0;
0.0;
0.0;
0.0;
0.0;
0.0;
0.0;
0.0;
0.0;
0.0;
0.0;
0.0;
0.0;
0.0;
0.0;
0.0;
0.0;
0.0;
0.0;
0.0;
0.0;
0.0;
0.0;
0.0;
0.0;
0.0;
0.0;
0.0;
0.0;
0.0;
0.0;
0.0;
0.0;
0.0;
0.0;
0.0;
0.0;
0.0;
0.0;
0.0;
0.0;
0.0;
0.0;
0.0;
0.0;
0.0;
0.0;
0.0;
0.0;
0.0;
0.0;
0.0;
0.0;
0.0;
0.0;
0.0;
0.0;
0.0;
0.0;
0.0;
0.0;
0.0;
0.0;
0.0;
0.0;
0.0;
0.0;
0.0;
0.0;
0.0;
0.0;
0.0;
0.0;
0.0;
0.0;
0.0;
0.0;
0.0;
0.0;
0.0;
0.0;
0.0;
0.0;
0.0;
0.0;
0.0;
0.0;
0.0;
0.0;
0.0;
0.0;
0.0;
0.0;
0.0;
0.0;
0.0;
0.0;
0.0;
0.0;
0.0;
0.0;
0.0;
0.0;
0.0;
0.0;
0.0;
0.0;
0.0;
0.0;
0.0;
0.0;
0.0;
0.0;
0.0;
0.0;
0.0;
0.0;
0.0;
0.0;
0.0;
0.0;
0.0;
0.0;
0.0;
0.0;
0.0;
0.0;
0.0;
0.0;
0.0;
0.0;
0.0;
0.0;
0.0;
0.0;
0.0;
0.0;
0.0;
0.0;
0.0;
0.0;
0.0;
0.0;
0.0;
0.0;
0.0;
0.0;
0.0;
0.0;
0.0;
0.0;
0.0;
0.0;
0.0;
0.0;
0.0;
0.0;
0.0;
0.0;
0.0;
0.0;
0.0;
0.0;
0.0;
0.0;
0.0;
0.0;
0.0;
0.0;
0.0;
0.0;
0.0;
0.0;
0.0;
0.0;
0.0;
0.0;
0.0;
0.0;
0.0;
0.0;
0.0;
0.0;
0.0;
0.0;
0.0;
0.0;
0.0;
0.0;
0.0;
0.0;
0.0;
0.0;
0.0;
0.0;
0.0;
0.0;
0.0;
0.0;
0.0;
0.0;
0.0;
0.0;
0.0;
0.0;
0.0;
0.0;
0.0;
0.0;
0.0;
0.0;
0.0;
0.0;
0.0;
0.0;
0.0;
0.0;
0.0;
0.0;
0.0;
0.0;
0.0;
0.0;
0.0;
0.0;
0.0;
0.0;
0.0;
0.0;
0.0;
0.0;
0.0;
0.0;
0.0;
0.0;
0.0;
0.0;
0.0;
0.0;
0.0;
0.0;
0.0;
0.0;
0.0;
0.0;
0.0;
0.0;
0.0;
0.0;
0.0;
0.0;
0.0;
0.0;
0.0;
0.0;
0.0;
0.0;
0.0;
0.0;
0.0;
0.0;
0.0;
0.0;
0.0;
0.0;
0.0;
0.0;
0.0;
0.0;
0.0;
0.0;
0.0;
0.0;
0.0;
0.0;
0.0;
0.0;
0.0;
0.0;
0.0;
0.0;
0.0;
0.0;
0.0;
0.0;
0.0;
0.0;
0.0;
0.0;
0.0;
0.0;
0.0;
0.0;
0.0;
0.0;
0.0;
0.0;
0.0;
0.0;
0.0;
0.0;
0.0;
0.0;
0.0;
0.0;
0.0;
0.0;
0.0;
0.0;
0.0;
0.0;
0.0;
0.0;
0.0;
0.0;
0.0;
0.0;
0.0;
0.0;
0.0;
0.0;
0.0;
0.0;
0.0;
0.0;
0.0;
0.0;
0.0;
0.0;
0.0;
0.0;
0.0;
0.0;
0.0;

</solute>
<solute name="dLuxS" unit="g.L-1" resolution="8.0" nI="33" nJ="33" nK="1">
0.0;
0.0;
0.0;
0.0;
0.0;
0.0;
0.0;
0.0;
0.0;
0.0;
0.0;
0.0;
0.0;
0.0;
0.0;
0.0;
0.0;
0.0;
0.0;
0.0;
0.0;
0.0;
0.0;
0.0;
0.0;
0.0;
0.0;
0.0;
0.0;
0.0;
0.0;
0.0;
0.0;
0.0;
0.0;
0.0;
0.0;
84.97703912367854;
102.7553708505915;
103.64956523096042;
90.89379894287956;
137.1065113858697;
106.10648736979311;
103.17952958768133;
109.3632558133989;
99.33898702542129;
132.2645654692049;
37.44123331832432;
42.72612639506209;
132.2384430750925;
72.33977689735569;
113.23856794087344;
132.35248048993267;
100.25420748485055;
100.75446063705749;
88.3941172935526;
108.90317568739349;
116.24409323436994;
73.9044223894625;
80.27821883857541;
88.95457392607688;
115.29674629161832;
126.26966041270983;
99.95996705885814;
86.15870649985797;
96.53615892566283;
113.95231570157839;
67.03412349647937;
0.0;
0.0;
0.0;
0.0;
49.45589199636576;
72.52437662170867;
109.72424645658552;
81.84771295556598;
90.64504586466872;
91.97845855154642;
114.28704480152749;
71.92452795102871;
98.23561537379652;
87.33720318184663;
92.3180781422477;
43.60113724537716;
85.97172292714309;
89.34070225250856;
100.09087947296221;
92.98607419943232;
92.51592363067662;
97.82877901897318;
93.25491505202103;
131.12747278001405;
58.020344837585924;
101.32441753903662;
102.18815188675288;
50.58689430588224;
61.28824640598734;
85.4696512921615;
102.7091424164243;
49.41900608777551;
104.37188827495413;
68.7497232043317;
20.354079756272625;
0.0;
0.0;
0.0;
0.0;
47.919688052843796;
102.12537376088656;
96.37171724362744;
88.19772767870059;
106.59185113420511;
83.007314499357;
83.61481755338518;
84.66715972730707;
56.81787482614489;
76.00197256192988;
45.95636936644631;
66.85235139806386;
72.66194107270393;
53.59646063786527;
100.83091125994675;
108.67156292726895;
80.45029137696217;
99.6081640297345;
84.78938532937661;
95.58890329556672;
96.8657054026331;
75.61541376427017;
83.71930597747622;
15.954577030929643;
90.36000333448824;
133.30006162972575;
91.18443615214996;
63.19152141517955;
17.048151406930966;
84.80896730797977;
38.263809464898586;
16.824100001718342;
0.0;
0.0;
0.0;
13.95475738580186;
82.64076927728873;
70.09368690960375;
85.38763484909364;
95.42321745576265;
105.33639907557219;
107.92349296139052;
104.60950311964986;
105.24678728089268;
96.5946292688479;
83.41105236987315;
87.76611814491929;
79.73002868351657;
99.31331459568871;
78.89631748168075;
89.92133046443142;
73.618719412695;
73.06903904139156;
83.51701684413545;
78.25421389600014;
92.42850815134643;
75.52115338449202;
54.0125212833593;
78.54978275821142;
95.37944906026567;
91.48114327359175;
73.93152216186068;
73.57633231549558;
0.0;
17.001706632179065;
0.0;
0.0;
0.0;
0.0;
14.11910173247789;
31.291146862811427;
101.7575607295395;
42.7324622853088;
33.84626465685057;
88.59121449724485;
49.34353152117072;
73.4995737338154;
102.34375143141364;
110.90315460619598;
93.47101622534359;
50.50036070411389;
69.4014604083505;
78.26220683375172;
86.60972553436486;
92.0646340285553;
120.5404636199039;
91.49325013612787;
120.21002852214973;
92.04154506444763;
97.45193696049704;
86.25268413712561;
68.13502388749833;
58.314367068489204;
31.325817322300583;
68.42130352342205;
82.50974122419225;
79.17584712624904;
55.093383582682705;
0.0;
0.0;
0.0;
0.0;
0.0;
0.0;
0.0;
22.40259473016192;
0.0;
0.0;
24.528376923257117;
58.841474066992376;
130.58874765415823;
59.16619597045478;
92.73283080710493;
104.31534725598851;
69.23236253698283;
22.08497914191921;
31.599109143623643;
77.78979091354321;
53.018706322058414;
22.184767594601798;
67.03682291705266;
107.49292831051109;
75.19148190059079;
79.17977089603866;
95.20605027191968;
69.62095302247882;
59.35022073990514;
52.97718223518645;
21.948592991875678;
85.59099505432087;
88.57217347588144;
88.36326945209503;
16.396843356052504;
0.0;
0.0;
0.0;
0.0;
0.0;
0.0;
0.0;
0.0;
0.0;
0.0;
0.0;
74.35809608825605;
15.772482601668123;
0.0;
58.64088364426706;
70.51486586455371;
69.86227039449511;
20.87105118642865;
21.930126168379086;
18.84158181496497;
0.0;
39.99645863316901;
69.97602457622149;
74.12348105152088;
55.14855176732628;
96.20238219105109;
65.21761988278973;
79.71814142042521;
67.93308394929412;
0.0;
0.0;
73.95416281819675;
98.8790369904587;
67.65302432871032;
41.7412293896715;
0.0;
0.0;
0.0;
0.0;
0.0;
0.0;
0.0;
0.0;
0.0;
0.0;
0.0;
40.726219537183404;
27.174305617607597;
0.0;
32.9801422669553;
62.99144417450326;
27.548057400362453;
34.857398347213255;
0.0;
0.0;
0.0;
0.0;
0.0;
19.834741382999113;
33.738496047622114;
29.162090690288586;
54.40241787880582;
0.0;
24.587669833715573;
0.0;
0.0;
0.0;
0.0;
0.0;
0.0;
0.0;
0.0;
0.0;
0.0;
0.0;
0.0;
0.0;
0.0;
0.0;
0.0;
0.0;
0.0;
0.0;
0.0;
0.0;
0.0;
0.0;
0.0;
0.0;
0.0;
0.0;
0.0;
0.0;
0.0;
0.0;
0.0;
0.0;
0.0;
0.0;
0.0;
0.0;
0.0;
0.0;
0.0;
0.0;
0.0;
0.0;
0.0;
0.0;
0.0;
0.0;
0.0;
0.0;
0.0;
0.0;
0.0;
0.0;
0.0;
0.0;
0.0;
0.0;
0.0;
0.0;
0.0;
0.0;
0.0;
0.0;
0.0;
0.0;
0.0;
0.0;
0.0;
0.0;
0.0;
0.0;
0.0;
0.0;
0.0;
0.0;
0.0;
0.0;
0.0;
0.0;
0.0;
0.0;
0.0;
0.0;
0.0;
0.0;
0.0;
0.0;
0.0;
0.0;
0.0;
0.0;
0.0;
0.0;
0.0;
0.0;
0.0;
0.0;
0.0;
0.0;
0.0;
0.0;
0.0;
0.0;
0.0;
0.0;
0.0;
0.0;
0.0;
0.0;
0.0;
0.0;
0.0;
0.0;
0.0;
0.0;
0.0;
0.0;
0.0;
0.0;
0.0;
0.0;
0.0;
0.0;
0.0;
0.0;
0.0;
0.0;
0.0;
0.0;
0.0;
0.0;
0.0;
0.0;
0.0;
0.0;
0.0;
0.0;
0.0;
0.0;
0.0;
0.0;
0.0;
0.0;
0.0;
0.0;
0.0;
0.0;
0.0;
0.0;
0.0;
0.0;
0.0;
0.0;
0.0;
0.0;
0.0;
0.0;
0.0;
0.0;
0.0;
0.0;
0.0;
0.0;
0.0;
0.0;
0.0;
0.0;
0.0;
0.0;
0.0;
0.0;
0.0;
0.0;
0.0;
0.0;
0.0;
0.0;
0.0;
0.0;
0.0;
0.0;
0.0;
0.0;
0.0;
0.0;
0.0;
0.0;
0.0;
0.0;
0.0;
0.0;
0.0;
0.0;
0.0;
0.0;
0.0;
0.0;
0.0;
0.0;
0.0;
0.0;
0.0;
0.0;
0.0;
0.0;
0.0;
0.0;
0.0;
0.0;
0.0;
0.0;
0.0;
0.0;
0.0;
0.0;
0.0;
0.0;
0.0;
0.0;
0.0;
0.0;
0.0;
0.0;
0.0;
0.0;
0.0;
0.0;
0.0;
0.0;
0.0;
0.0;
0.0;
0.0;
0.0;
0.0;
0.0;
0.0;
0.0;
0.0;
0.0;
0.0;
0.0;
0.0;
0.0;
0.0;
0.0;
0.0;
0.0;
0.0;
0.0;
0.0;
0.0;
0.0;
0.0;
0.0;
0.0;
0.0;
0.0;
0.0;
0.0;
0.0;
0.0;
0.0;
0.0;
0.0;
0.0;
0.0;
0.0;
0.0;
0.0;
0.0;
0.0;
0.0;
0.0;
0.0;
0.0;
0.0;
0.0;
0.0;
0.0;
0.0;
0.0;
0.0;
0.0;
0.0;
0.0;
0.0;
0.0;
0.0;
0.0;
0.0;
0.0;
0.0;
0.0;
0.0;
0.0;
0.0;
0.0;
0.0;
0.0;
0.0;
0.0;
0.0;
0.0;
0.0;
0.0;
0.0;
0.0;
0.0;
0.0;
0.0;
0.0;
0.0;
0.0;
0.0;
0.0;
0.0;
0.0;
0.0;
0.0;
0.0;
0.0;
0.0;
0.0;
0.0;
0.0;
0.0;
0.0;
0.0;
0.0;
0.0;
0.0;
0.0;
0.0;
0.0;
0.0;
0.0;
0.0;
0.0;
0.0;
0.0;
0.0;
0.0;
0.0;
0.0;
0.0;
0.0;
0.0;
0.0;
0.0;
0.0;
0.0;
0.0;
0.0;
0.0;
0.0;
0.0;
0.0;
0.0;
0.0;
0.0;
0.0;
0.0;
0.0;
0.0;
0.0;
0.0;
0.0;
0.0;
0.0;
0.0;
0.0;
0.0;
0.0;
0.0;
0.0;
0.0;
0.0;
0.0;
0.0;
0.0;
0.0;
0.0;
0.0;
0.0;
0.0;
0.0;
0.0;
0.0;
0.0;
0.0;
0.0;
0.0;
0.0;
0.0;
0.0;
0.0;
0.0;
0.0;
0.0;
0.0;
0.0;
0.0;
0.0;
0.0;
0.0;
0.0;
0.0;
0.0;
0.0;
0.0;
0.0;
0.0;
0.0;
0.0;
0.0;
0.0;
0.0;
0.0;
0.0;
0.0;
0.0;
0.0;
0.0;
0.0;
0.0;
0.0;
0.0;
0.0;
0.0;
0.0;
0.0;
0.0;
0.0;
0.0;
0.0;
0.0;
0.0;
0.0;
0.0;
0.0;
0.0;
0.0;
0.0;
0.0;
0.0;
0.0;
0.0;
0.0;
0.0;
0.0;
0.0;
0.0;
0.0;
0.0;
0.0;
0.0;
0.0;
0.0;
0.0;
0.0;
0.0;
0.0;
0.0;
0.0;
0.0;
0.0;
0.0;
0.0;
0.0;
0.0;
0.0;
0.0;
0.0;
0.0;
0.0;
0.0;
0.0;
0.0;
0.0;
0.0;
0.0;
0.0;
0.0;
0.0;
0.0;
0.0;
0.0;
0.0;
0.0;
0.0;
0.0;
0.0;
0.0;
0.0;
0.0;
0.0;
0.0;
0.0;
0.0;
0.0;
0.0;
0.0;
0.0;
0.0;
0.0;
0.0;
0.0;
0.0;
0.0;
0.0;
0.0;
0.0;
0.0;
0.0;
0.0;
0.0;
0.0;
0.0;
0.0;
0.0;
0.0;
0.0;
0.0;
0.0;
0.0;
0.0;
0.0;
0.0;
0.0;
0.0;
0.0;
0.0;
0.0;
0.0;
0.0;
0.0;
0.0;
0.0;
0.0;
0.0;
0.0;
0.0;
0.0;
0.0;
0.0;
0.0;
0.0;
0.0;
0.0;
0.0;
0.0;
0.0;
0.0;
0.0;
0.0;
0.0;
0.0;
0.0;
0.0;
0.0;
0.0;
0.0;
0.0;
0.0;
0.0;
0.0;
0.0;
0.0;
0.0;
0.0;
0.0;
0.0;
0.0;
0.0;
0.0;
0.0;
0.0;
0.0;
0.0;
0.0;
0.0;
0.0;
0.0;
0.0;
0.0;
0.0;
0.0;
0.0;
0.0;
0.0;
0.0;
0.0;
0.0;
0.0;
0.0;
0.0;
0.0;
0.0;
0.0;
0.0;
0.0;
0.0;
0.0;
0.0;
0.0;
0.0;
0.0;
0.0;
0.0;
0.0;
0.0;
0.0;
0.0;
0.0;
0.0;
0.0;
0.0;
0.0;
0.0;
0.0;
0.0;
0.0;
0.0;
0.0;
0.0;
0.0;
0.0;
0.0;
0.0;
0.0;
0.0;
0.0;
0.0;
0.0;
0.0;
0.0;
0.0;
0.0;
0.0;
0.0;
0.0;
0.0;
0.0;
0.0;
0.0;
0.0;
0.0;
0.0;
0.0;
0.0;
0.0;
0.0;
0.0;
0.0;
0.0;
0.0;
0.0;
0.0;
0.0;
0.0;
0.0;
0.0;
0.0;
0.0;
0.0;
0.0;
0.0;
0.0;
0.0;
0.0;
0.0;
0.0;
0.0;
0.0;
0.0;
0.0;
0.0;
0.0;
0.0;
0.0;
0.0;
0.0;
0.0;
0.0;
0.0;
0.0;
0.0;
0.0;
0.0;
0.0;
0.0;
0.0;
0.0;
0.0;
0.0;
0.0;
0.0;
0.0;
0.0;
0.0;
0.0;
0.0;
0.0;
0.0;
0.0;
0.0;
0.0;
0.0;
0.0;
0.0;
0.0;
0.0;
0.0;
0.0;
0.0;
0.0;
0.0;
0.0;
0.0;
0.0;
0.0;
0.0;
0.0;
0.0;
0.0;
0.0;
0.0;
0.0;
0.0;
0.0;
0.0;
0.0;
0.0;
0.0;
0.0;
0.0;
0.0;
0.0;
0.0;
0.0;
0.0;
0.0;
0.0;
0.0;
0.0;
0.0;
0.0;
0.0;
0.0;
0.0;
0.0;
0.0;
0.0;
0.0;
0.0;
0.0;
0.0;
0.0;
0.0;
0.0;
0.0;
0.0;
0.0;
0.0;
0.0;
0.0;
0.0;
0.0;
0.0;
0.0;
0.0;
0.0;
0.0;
0.0;
0.0;
0.0;
0.0;
0.0;
0.0;
0.0;
0.0;
0.0;
0.0;
0.0;
0.0;
0.0;
0.0;
0.0;
0.0;
0.0;
0.0;
0.0;
0.0;
0.0;
0.0;
0.0;
0.0;
0.0;
0.0;
0.0;
0.0;
0.0;
0.0;
0.0;
0.0;
0.0;
0.0;
0.0;
0.0;
0.0;
0.0;
0.0;
0.0;
0.0;
0.0;
0.0;
0.0;
0.0;
0.0;
0.0;
0.0;
0.0;
0.0;
0.0;
0.0;
0.0;
0.0;
0.0;
0.0;
0.0;
0.0;
0.0;
0.0;
0.0;
0.0;
0.0;
0.0;
0.0;
0.0;
0.0;
0.0;
0.0;
0.0;
0.0;
0.0;
0.0;
0.0;
0.0;
0.0;
0.0;
0.0;
0.0;
0.0;
0.0;
0.0;
0.0;
0.0;
0.0;
0.0;
0.0;
0.0;
0.0;
0.0;
0.0;
0.0;
0.0;
0.0;
0.0;
0.0;
0.0;
0.0;
0.0;
0.0;
0.0;
0.0;
0.0;
0.0;
0.0;
0.0;
0.0;
0.0;
0.0;
0.0;
0.0;
0.0;
0.0;
0.0;
0.0;
0.0;
0.0;
0.0;
0.0;
0.0;
0.0;
0.0;
0.0;
0.0;
0.0;
0.0;
0.0;
0.0;
0.0;
0.0;
0.0;
0.0;
0.0;
0.0;
0.0;
0.0;
0.0;
0.0;
0.0;
0.0;
0.0;
0.0;
0.0;
0.0;
0.0;
0.0;
0.0;

</solute>
<solute name="totalBiomass" unit="g.L-1" resolution="8.0" nI="33" nJ="33" nK="1">
0.0;
64.64518329830311;
117.83782196084857;
102.7553708505915;
103.64956523096042;
90.89379894287958;
137.1065113858697;
106.1064873697931;
103.17952958768134;
109.3632558133989;
99.33898702542128;
132.2645654692049;
37.44123331832432;
42.726126395062096;
132.2384430750925;
72.33977689735569;
113.23856794087344;
132.35248048993265;
100.25420748485055;
100.75446063705748;
88.3941172935526;
108.90317568739349;
116.24409323436994;
73.9044223894625;
80.27821883857541;
88.95457392607688;
115.29674629161833;
126.26966041270983;
99.95996705885815;
121.60056501396718;
96.53615892566283;
113.95231570157839;
91.22855829029294;
89.13424700463514;
0.0;
64.64518329830311;
64.64518329830311;
117.83782196084857;
102.7553708505915;
103.64956523096042;
90.89379894287958;
137.1065113858697;
106.1064873697931;
103.17952958768134;
109.3632558133989;
99.33898702542128;
132.2645654692049;
37.44123331832432;
42.726126395062096;
132.2384430750925;
72.33977689735569;
113.23856794087344;
132.35248048993265;
100.25420748485055;
100.75446063705748;
88.3941172935526;
108.90317568739349;
116.24409323436994;
73.9044223894625;
80.27821883857541;
88.95457392607688;
115.29674629161833;
126.26966041270983;
99.95996705885815;
121.60056501396718;
96.53615892566283;
113.95231570157839;
91.22855829029294;
89.13424700463514;
89.13424700463514;
38.18891683100577;
38.18891683100577;
86.0106292674983;
72.52437662170868;
109.72424645658552;
81.84771295556598;
90.64504586466873;
91.97845855154642;
114.2870448015275;
71.92452795102871;
98.23561537379652;
87.33720318184663;
92.3180781422477;
43.60113724537716;
85.97172292714309;
89.34070225250856;
100.09087947296221;
92.98607419943232;
92.51592363067661;
97.82877901897318;
93.25491505202103;
131.12747278001405;
58.02034483758593;
101.32441753903662;
102.18815188675286;
50.58689430588224;
61.28824640598734;
85.46965129216149;
102.70914241642431;
80.38478232583363;
151.51997026537117;
68.7497232043317;
121.59840737192701;
59.28548445749749;
59.28548445749749;
94.28251814240471;
94.28251814240471;
92.261217928349;
102.12537376088656;
96.37171724362746;
88.19772767870059;
106.59185113420511;
83.007314499357;
83.6148175533852;
84.66715972730707;
56.81787482614489;
76.00197256192988;
45.95636936644631;
66.85235139806386;
72.66194107270393;
53.59646063786527;
100.83091125994673;
108.67156292726895;
80.45029137696217;
99.6081640297345;
84.78938532937661;
95.58890329556672;
96.86570540263308;
75.61541376427017;
83.71930597747622;
15.954577030929643;
90.36000333448823;
133.30006162972577;
91.18443615214996;
99.51429025596933;
73.86610598150169;
84.80896730797977;
95.49896729715275;
59.52376303214041;
59.52376303214041;
57.66881844793362;
57.66881844793362;
78.21990581428302;
82.64076927728873;
84.99611673458097;
85.38763484909364;
95.42321745576267;
105.33639907557219;
107.92349296139054;
104.60950311964986;
105.24678728089268;
96.5946292688479;
83.41105236987315;
87.76611814491929;
79.73002868351657;
99.31331459568871;
78.89631748168075;
89.92133046443142;
73.618719412695;
73.06903904139156;
83.51701684413545;
78.25421389600015;
92.42850815134643;
75.52115338449202;
54.0125212833593;
78.54978275821142;
95.37944906026567;
91.48114327359175;
73.93152216186068;
125.01584641272908;
92.72818135476216;
113.65620154678919;
54.4366247201322;
33.157862066205034;
33.157862066205034;
69.76674022513232;
69.76674022513232;
71.86969151390417;
101.7575607295395;
91.20487674674332;
85.42143936067428;
88.59121449724485;
49.34353152117072;
73.4995737338154;
102.34375143141362;
110.90315460619595;
93.47101622534359;
50.50036070411389;
69.4014604083505;
78.26220683375172;
86.60972553436486;
92.0646340285553;
120.5404636199039;
91.49325013612787;
120.21002852214973;
92.04154506444763;
97.45193696049702;
86.25268413712561;
68.13502388749833;
58.314367068489204;
31.325817322300583;
68.42130352342205;
82.50974122419225;
79.17584712624904;
96.09094502780587;
92.55247319882135;
100.80462001897602;
110.29191605360316;
94.49577657629446;
94.49577657629446;
77.91240549159691;
77.91240549159691;
68.19695048595125;
23.109084787526655;
103.82952322303605;
109.811362084966;
58.841474066992376;
130.58874765415825;
59.16619597045478;
92.73283080710493;
104.3153472559885;
69.23236253698283;
22.08497914191921;
31.599109143623643;
77.78979091354321;
71.95653922485695;
22.184767594601798;
67.03682291705266;
107.49292831051109;
75.19148190059079;
79.17977089603866;
95.20605027191968;
69.62095302247882;
59.35022073990514;
52.97718223518645;
21.948592991875678;
85.59099505432087;
88.57217347588144;
88.36326945209501;
92.22987782465748;
90.75003266401812;
90.34515835988525;
120.10122147814018;
63.4249285323488;
63.4249285323488;
0.0;
0.0;
0.0;
51.25201225342117;
60.44390524121056;
47.107102006248;
74.35809608825603;
68.3442961557947;
96.36048191108763;
113.73149748564626;
70.51486586455373;
69.86227039449511;
20.87105118642865;
21.930126168379086;
77.4456977827803;
60.18392592851263;
39.99645863316901;
69.97602457622149;
74.12348105152087;
55.14855176732628;
96.20238219105109;
65.21761988278973;
79.71814142042521;
67.93308394929412;
0.0;
0.0;
73.95416281819675;
98.87903699045869;
67.65302432871032;
60.15008550321659;
116.57849788631694;
75.39989348654063;
80.5007190941367;
76.06709929982787;
76.06709929982787;
21.763106969645257;
21.763106969645257;
0.0;
0.0;
54.987664569823835;
47.9894455814149;
40.726219537183404;
64.48005465486543;
35.62345266974692;
68.0706760430343;
62.99144417450325;
27.548057400362453;
34.857398347213255;
0.0;
22.67138838300285;
44.59096120530408;
0.0;
0.0;
19.834741382999113;
33.738496047622114;
72.24381123629011;
54.40241787880582;
0.0;
24.587669833715573;
0.0;
0.0;
0.0;
0.0;
0.0;
48.370824117630804;
98.7185741611138;
102.14222088661343;
91.7593816255401;
55.549928776233074;
55.549928776233074;
0.0;
0.0;
0.0;
0.0;
27.09613445002251;
27.597986232481464;
0.0;
0.0;
0.0;
0.0;
0.0;
0.0;
0.0;
0.0;
0.0;
0.0;
0.0;
0.0;
0.0;
0.0;
0.0;
0.0;
0.0;
0.0;
0.0;
0.0;
0.0;
0.0;
0.0;
24.16725932545968;
89.78308686474686;
95.95724566647637;
71.43040223046998;
47.59732125945543;
47.59732125945543;
0.0;
0.0;
0.0;
0.0;
26.74071123508846;
0.0;
0.0;
0.0;
0.0;
0.0;
0.0;
0.0;
0.0;
0.0;
0.0;
0.0;
0.0;
0.0;
0.0;
0.0;
0.0;
0.0;
0.0;
0.0;
0.0;
0.0;
0.0;
0.0;
0.0;
0.0;
59.3260133452048;
114.746715087808;
87.17992041576538;
62.49049650157569;
62.49049650157569;
0.0;
0.0;
0.0;
0.0;
25.590452689861028;
0.0;
0.0;
0.0;
0.0;
0.0;
0.0;
0.0;
0.0;
0.0;
0.0;
0.0;
0.0;
0.0;
0.0;
0.0;
0.0;
0.0;
0.0;
0.0;
0.0;
0.0;
0.0;
0.0;
0.0;
0.0;
13.123704098217148;
88.93966407463043;
67.8016293816953;
88.69562184211189;
88.69562184211189;
0.0;
0.0;
23.8973280206634;
0.0;
0.0;
0.0;
0.0;
0.0;
0.0;
0.0;
0.0;
0.0;
0.0;
0.0;
0.0;
0.0;
0.0;
0.0;
0.0;
0.0;
0.0;
0.0;
0.0;
0.0;
0.0;
0.0;
0.0;
0.0;
0.0;
0.0;
0.0;
87.55120952629314;
73.8962195936154;
94.5402593689714;
94.5402593689714;
0.0;
0.0;
0.0;
0.0;
0.0;
0.0;
0.0;
0.0;
0.0;
0.0;
0.0;
0.0;
0.0;
0.0;
0.0;
0.0;
0.0;
0.0;
0.0;
0.0;
0.0;
0.0;
0.0;
0.0;
0.0;
0.0;
0.0;
0.0;
0.0;
0.0;
0.0;
19.022911972054878;
87.52199968419892;
74.2271580491525;
74.2271580491525;
0.0;
0.0;
0.0;
0.0;
0.0;
0.0;
0.0;
0.0;
0.0;
0.0;
0.0;
0.0;
0.0;
0.0;
0.0;
0.0;
0.0;
0.0;
0.0;
0.0;
0.0;
0.0;
0.0;
0.0;
0.0;
0.0;
0.0;
0.0;
11.041143669944661;
0.0;
0.0;
38.76319278818297;
59.21615390103571;
67.47609869498092;
67.47609869498092;
0.0;
0.0;
0.0;
0.0;
0.0;
0.0;
0.0;
0.0;
0.0;
0.0;
0.0;
0.0;
0.0;
0.0;
0.0;
0.0;
0.0;
0.0;
0.0;
0.0;
0.0;
0.0;
0.0;
0.0;
0.0;
0.0;
0.0;
0.0;
0.0;
0.0;
0.0;
0.0;
0.0;
25.594540942988562;
25.594540942988562;
0.0;
0.0;
0.0;
0.0;
0.0;
0.0;
0.0;
0.0;
0.0;
0.0;
0.0;
0.0;
15.45335086665615;
0.0;
0.0;
0.0;
0.0;
0.0;
0.0;
0.0;
0.0;
0.0;
0.0;
0.0;
0.0;
0.0;
0.0;
0.0;
0.0;
0.0;
0.0;
0.0;
0.0;
0.0;
0.0;
0.0;
0.0;
0.0;
0.0;
0.0;
0.0;
0.0;
0.0;
0.0;
0.0;
0.0;
0.0;
0.0;
0.0;
0.0;
0.0;
0.0;
0.0;
0.0;
0.0;
0.0;
0.0;
0.0;
0.0;
0.0;
0.0;
0.0;
0.0;
0.0;
0.0;
0.0;
0.0;
0.0;
0.0;
0.0;
22.225394351946868;
22.225394351946868;
0.0;
0.0;
17.167467469941844;
0.0;
0.0;
0.0;
0.0;
0.0;
0.0;
0.0;
0.0;
0.0;
0.0;
0.0;
0.0;
0.0;
0.0;
0.0;
0.0;
0.0;
0.0;
0.0;
0.0;
0.0;
0.0;
0.0;
0.0;
0.0;
0.0;
0.0;
0.0;
19.084744342528122;
19.084744342528122;
0.0;
0.0;
0.0;
0.0;
0.0;
0.0;
0.0;
0.0;
0.0;
0.0;
0.0;
0.0;
0.0;
0.0;
0.0;
0.0;
9.938135118324084;
0.0;
0.0;
0.0;
0.0;
0.0;
0.0;
0.0;
0.0;
0.0;
0.0;
0.0;
0.0;
0.0;
0.0;
0.0;
0.0;
0.0;
0.0;
0.0;
0.0;
0.0;
0.0;
0.0;
0.0;
0.0;
0.0;
0.0;
0.0;
0.0;
0.0;
0.0;
0.0;
0.0;
0.0;
0.0;
0.0;
0.0;
0.0;
0.0;
0.0;
0.0;
0.0;
0.0;
0.0;
0.0;
0.0;
0.0;
14.733680143525497;
0.0;
0.0;
0.0;
0.0;
0.0;
0.0;
0.0;
0.0;
0.0;
0.0;
0.0;
0.0;
0.0;
0.0;
0.0;
0.0;
0.0;
0.0;
0.0;
0.0;
0.0;
0.0;
0.0;
0.0;
0.0;
0.0;
0.0;
0.0;
0.0;
0.0;
0.0;
0.0;
0.0;
0.0;
0.0;
0.0;
0.0;
0.0;
0.0;
0.0;
0.0;
0.0;
0.0;
0.0;
0.0;
0.0;
18.628855633874764;
0.0;
0.0;
0.0;
0.0;
0.0;
0.0;
0.0;
0.0;
0.0;
0.0;
0.0;
0.0;
0.0;
0.0;
0.0;
0.0;
0.0;
0.0;
0.0;
0.0;
0.0;
0.0;
20.064482493668862;
0.0;
0.0;
0.0;
0.0;
0.0;
0.0;
0.0;
0.0;
0.0;
0.0;
0.0;
0.0;
0.0;
0.0;
0.0;
0.0;
0.0;
0.0;
0.0;
0.0;
0.0;
0.0;
0.0;
0.0;
0.0;
0.0;
0.0;
0.0;
0.0;
0.0;
0.0;
0.0;
0.0;
0.0;
0.0;
0.0;
0.0;
0.0;
0.0;
0.0;
0.0;
0.0;
0.0;
0.0;
0.0;
0.0;
0.0;
0.0;
0.0;
0.0;
0.0;
0.0;
0.0;
0.0;
0.0;
0.0;
0.0;
0.0;
0.0;
0.0;
0.0;
0.0;
0.0;
0.0;
0.0;
0.0;
0.0;
0.0;
0.0;
0.0;
0.0;
0.0;
0.0;
0.0;
0.0;
0.0;
0.0;
0.0;
0.0;
0.0;
0.0;
0.0;
0.0;
0.0;
0.0;
0.0;
0.0;
0.0;
0.0;
0.0;
0.0;
0.0;
0.0;
0.0;
0.0;
0.0;
0.0;
0.0;
0.0;
0.0;
0.0;
0.0;
0.0;
0.0;
0.0;
0.0;
0.0;
0.0;
0.0;
0.0;
0.0;
0.0;
0.0;
0.0;
0.0;
0.0;
0.0;
0.0;
0.0;
0.0;
0.0;
0.0;
0.0;
0.0;
0.0;
0.0;
0.0;
0.0;
0.0;
0.0;
0.0;
0.0;
0.0;
0.0;
0.0;
0.0;
0.0;
0.0;
0.0;
0.0;
0.0;
0.0;
0.0;
0.0;
0.0;
0.0;
0.0;
0.0;
0.0;
0.0;
0.0;
0.0;
0.0;
0.0;
0.0;
0.0;
0.0;
0.0;
0.0;
0.0;
0.0;
0.0;
0.0;
0.0;
0.0;
0.0;
0.0;
0.0;
0.0;
0.0;
0.0;
0.0;
0.0;
0.0;
0.0;
0.0;
0.0;
0.0;
0.0;
0.0;
0.0;
0.0;
0.0;
0.0;
0.0;
0.0;
0.0;
0.0;
0.0;
0.0;
0.0;
0.0;
0.0;
0.0;
0.0;
0.0;
0.0;
0.0;
0.0;
0.0;
0.0;
0.0;
0.0;
0.0;
0.0;
0.0;
0.0;
0.0;
0.0;
0.0;
0.0;
0.0;
0.0;
0.0;
0.0;
0.0;
0.0;
0.0;
0.0;
0.0;
0.0;
0.0;
0.0;
0.0;
0.0;
0.0;
0.0;
0.0;
0.0;
0.0;
0.0;
0.0;
0.0;
0.0;
0.0;
0.0;
0.0;
0.0;
0.0;
0.0;
0.0;
0.0;
0.0;
0.0;
0.0;
0.0;
0.0;
0.0;
0.0;
0.0;
0.0;
0.0;
0.0;
0.0;
0.0;
0.0;
0.0;
0.0;
0.0;
0.0;
0.0;
0.0;
0.0;
0.0;
0.0;
0.0;
0.0;
0.0;
0.0;
0.0;
0.0;
0.0;
0.0;
0.0;
0.0;
0.0;
0.0;
0.0;
0.0;
0.0;
0.0;
0.0;
0.0;
0.0;
0.0;
0.0;
0.0;
0.0;
0.0;
0.0;
0.0;
0.0;
0.0;
0.0;
0.0;
0.0;
0.0;
0.0;
0.0;
0.0;
0.0;
0.0;
0.0;
0.0;
0.0;
0.0;
0.0;
0.0;
0.0;
0.0;
0.0;
0.0;
0.0;
0.0;
0.0;
0.0;
0.0;
0.0;
0.0;
0.0;
0.0;
0.0;
0.0;
0.0;
0.0;
0.0;
0.0;
0.0;
0.0;
0.0;
0.0;
0.0;
0.0;
0.0;
0.0;
0.0;
0.0;
0.0;
0.0;
0.0;
0.0;
0.0;
0.0;
0.0;
0.0;
0.0;
0.0;
0.0;
0.0;
0.0;
0.0;
0.0;
0.0;
0.0;
0.0;
0.0;
0.0;
0.0;
0.0;
0.0;
0.0;
0.0;
0.0;
0.0;
0.0;
0.0;
0.0;
0.0;
0.0;
0.0;
0.0;
0.0;
0.0;
0.0;
0.0;
0.0;
0.0;
0.0;
0.0;
0.0;
0.0;
0.0;
0.0;
0.0;
0.0;
0.0;
0.0;
0.0;
0.0;
0.0;
0.0;
0.01;
0.01;
0.01;
0.01;
0.01;
0.01;
0.01;
0.01;
0.01;
0.01;
0.01;
0.01;
0.01;
0.01;
0.01;
0.01;
0.01;
0.01;
0.01;
0.01;
0.01;
0.01;
0.01;
0.01;
0.01;
0.01;
0.01;
0.01;
0.01;
0.01;
0.01;
0.01;
0.01;
0.0;

</solute>

</simulation>
</idynomics>